[
  {
    "timestamp": "10/19/2022 17:46:53.059410",
    "simulationTimeStamp": "11.5629",
    "logType": "Uav",
    "eventType": "Created",
    "logMessages": [
      "Uav Alfa created"
    ]
  },
  {
    "timestamp": "10/19/2022 17:46:53.067574",
    "simulationTimeStamp": "11.5629",
    "logType": "Uav",
    "eventType": "Created",
    "logMessages": [
      "Uav Bravo created"
    ]
  },
  {
    "timestamp": "10/19/2022 17:46:53.070575",
    "simulationTimeStamp": "11.5629",
    "logType": "Uav",
    "eventType": "Created",
    "logMessages": [
      "Uav Charlie created"
    ]
  },
  {
    "timestamp": "10/19/2022 17:46:53.072494",
    "simulationTimeStamp": "11.5629",
    "logType": "Uav",
    "eventType": "Created",
    "logMessages": [
      "Uav Delta created"
    ]
  },
  {
    "timestamp": "10/19/2022 17:46:53.075495",
    "simulationTimeStamp": "11.5629",
    "logType": "Uav",
    "eventType": "Created",
    "logMessages": [
      "Uav Echo created"
    ]
  },
  {
    "timestamp": "10/19/2022 17:46:53.077495",
    "simulationTimeStamp": "11.5629",
    "logType": "Uav",
    "eventType": "Created",
    "logMessages": [
      "Uav Frank created"
    ]
  },
  {
    "timestamp": "10/19/2022 17:46:53.080886",
    "simulationTimeStamp": "11.5629",
    "logType": "Uav",
    "eventType": "Created",
    "logMessages": [
      "Uav Golf created"
    ]
  },
  {
    "timestamp": "10/19/2022 17:46:53.082389",
    "simulationTimeStamp": "11.5629",
    "logType": "Uav",
    "eventType": "Created",
    "logMessages": [
      "Uav Hotel created"
    ]
  },
  {
    "timestamp": "10/19/2022 17:46:53.085845",
    "simulationTimeStamp": "11.5629",
    "logType": "Uav",
    "eventType": "Created",
    "logMessages": [
      "Uav India created"
    ]
  },
  {
    "timestamp": "10/19/2022 17:46:53.087391",
    "simulationTimeStamp": "11.5629",
    "logType": "Uav",
    "eventType": "Created",
    "logMessages": [
      "Uav John created"
    ]
  },
  {
    "timestamp": "10/19/2022 17:46:53.090409",
    "simulationTimeStamp": "11.5629",
    "logType": "Uav",
    "eventType": "Created",
    "logMessages": [
      "Uav Kilo created"
    ]
  },
  {
    "timestamp": "10/19/2022 17:46:53.093410",
    "simulationTimeStamp": "11.5629",
    "logType": "Uav",
    "eventType": "Created",
    "logMessages": [
      "Uav Lima created"
    ]
  },
  {
    "timestamp": "10/19/2022 17:46:53.095602",
    "simulationTimeStamp": "11.5629",
    "logType": "Uav",
    "eventType": "Created",
    "logMessages": [
      "Uav Mike created"
    ]
  },
  {
    "timestamp": "10/19/2022 17:46:53.098469",
    "simulationTimeStamp": "11.5629",
    "logType": "Uav",
    "eventType": "Created",
    "logMessages": [
      "Uav Nectar created"
    ]
  },
  {
    "timestamp": "10/19/2022 17:46:53.101098",
    "simulationTimeStamp": "11.5629",
    "logType": "Uav",
    "eventType": "Created",
    "logMessages": [
      "Uav Oscar created"
    ]
  },
  {
    "timestamp": "10/19/2022 17:46:53.103605",
    "simulationTimeStamp": "11.5629",
    "logType": "Uav",
    "eventType": "Created",
    "logMessages": [
      "Uav Papa created"
    ]
  },
  {
    "timestamp": "10/19/2022 17:46:57.958512",
    "simulationTimeStamp": "16.47034",
    "logType": "Uav",
    "eventType": "ConditionChanged",
    "logMessages": [
      "Uav Alfa condition changed to Hidden"
    ]
  },
  {
    "timestamp": "10/19/2022 17:46:57.964518",
    "simulationTimeStamp": "16.47034",
    "logType": "Uav",
    "eventType": "ConditionChanged",
    "logMessages": [
      "Uav Bravo condition changed to Hidden"
    ]
  },
  {
    "timestamp": "10/19/2022 17:46:57.964518",
    "simulationTimeStamp": "16.47034",
    "logType": "Uav",
    "eventType": "ConditionChanged",
    "logMessages": [
      "Uav Charlie condition changed to Hidden"
    ]
  },
  {
    "timestamp": "10/19/2022 17:46:57.964518",
    "simulationTimeStamp": "16.47034",
    "logType": "Uav",
    "eventType": "ConditionChanged",
    "logMessages": [
      "Uav Delta condition changed to Hidden"
    ]
  },
  {
    "timestamp": "10/19/2022 17:46:57.965519",
    "simulationTimeStamp": "16.47034",
    "logType": "Uav",
    "eventType": "ConditionChanged",
    "logMessages": [
      "Uav Echo condition changed to Enabled"
    ]
  },
  {
    "timestamp": "10/19/2022 17:46:57.965519",
    "simulationTimeStamp": "16.47034",
    "logType": "Uav",
    "eventType": "ConditionChanged",
    "logMessages": [
      "Uav Frank condition changed to Hidden"
    ]
  },
  {
    "timestamp": "10/19/2022 17:46:57.965519",
    "simulationTimeStamp": "16.47034",
    "logType": "Uav",
    "eventType": "ConditionChanged",
    "logMessages": [
      "Uav Golf condition changed to Hidden"
    ]
  },
  {
    "timestamp": "10/19/2022 17:46:57.966519",
    "simulationTimeStamp": "16.47034",
    "logType": "Uav",
    "eventType": "ConditionChanged",
    "logMessages": [
      "Uav Hotel condition changed to Hidden"
    ]
  },
  {
    "timestamp": "10/19/2022 17:46:57.966519",
    "simulationTimeStamp": "16.47034",
    "logType": "Uav",
    "eventType": "ConditionChanged",
    "logMessages": [
      "Uav India condition changed to Hidden"
    ]
  },
  {
    "timestamp": "10/19/2022 17:46:57.966519",
    "simulationTimeStamp": "16.47034",
    "logType": "Uav",
    "eventType": "ConditionChanged",
    "logMessages": [
      "Uav John condition changed to Enabled"
    ]
  },
  {
    "timestamp": "10/19/2022 17:46:57.966519",
    "simulationTimeStamp": "16.47034",
    "logType": "Uav",
    "eventType": "ConditionChanged",
    "logMessages": [
      "Uav Kilo condition changed to Hidden"
    ]
  },
  {
    "timestamp": "10/19/2022 17:46:57.966519",
    "simulationTimeStamp": "16.47034",
    "logType": "Uav",
    "eventType": "ConditionChanged",
    "logMessages": [
      "Uav Lima condition changed to Hidden"
    ]
  },
  {
    "timestamp": "10/19/2022 17:46:57.966519",
    "simulationTimeStamp": "16.47034",
    "logType": "Uav",
    "eventType": "ConditionChanged",
    "logMessages": [
      "Uav Mike condition changed to Hidden"
    ]
  },
  {
    "timestamp": "10/19/2022 17:46:57.967519",
    "simulationTimeStamp": "16.47034",
    "logType": "Uav",
    "eventType": "ConditionChanged",
    "logMessages": [
      "Uav Nectar condition changed to Hidden"
    ]
  },
  {
    "timestamp": "10/19/2022 17:46:57.967519",
    "simulationTimeStamp": "16.47034",
    "logType": "Uav",
    "eventType": "ConditionChanged",
    "logMessages": [
      "Uav Oscar condition changed to Hidden"
    ]
  },
  {
    "timestamp": "10/19/2022 17:46:57.967519",
    "simulationTimeStamp": "16.47034",
    "logType": "Uav",
    "eventType": "ConditionChanged",
    "logMessages": [
      "Uav Papa condition changed to Enabled"
    ]
  },
  {
    "timestamp": "10/19/2022 17:46:57.978945",
    "simulationTimeStamp": "16.47034",
    "logType": "Prompts",
    "eventType": "PromptMessageSent",
    "logMessages": [
      "Prompt Message: beginning Mission",
      "Allowed Response Time: 0.0"
    ]
  },
  {
    "timestamp": "10/19/2022 17:47:07.840856",
    "simulationTimeStamp": "26.34264",
    "logType": "Rerouting",
    "eventType": "Rerouting Options Requested",
    "logMessages": [
      " requested rerouting options for uav Echo",
      "Path start time: 10/19/2022 17:46:57.964518",
      "Rerouting is not needed"
    ]
  },
  {
    "timestamp": "10/19/2022 17:47:08.880295",
    "simulationTimeStamp": "27.3988",
    "logType": "Rerouting",
    "eventType": "Rerouting Option Previewed",
    "logMessages": [
      "Rerouting option previewed for Uav Echo ",
      "Path start time: 10/19/2022 17:46:57.964518",
      "Previewed route is good"
    ]
  },
  {
    "timestamp": "10/19/2022 17:47:14.304509",
    "simulationTimeStamp": "28.70102",
    "logType": "Rerouting",
    "eventType": "Rerouting Option Previewed",
    "logMessages": [
      "Rerouting option previewed for Uav Echo ",
      "Path start time: 10/19/2022 17:46:57.964518",
      "Previewed route is good"
    ]
  },
  {
    "timestamp": "10/19/2022 17:47:14.986910",
    "simulationTimeStamp": "29.38268",
    "logType": "Rerouting",
    "eventType": "Rerouting Option Previewed",
    "logMessages": [
      "Rerouting option previewed for Uav Echo ",
      "Path start time: 10/19/2022 17:46:57.964518",
      "Previewed route is good"
    ]
  },
  {
    "timestamp": "10/19/2022 17:47:18.032148",
    "simulationTimeStamp": "30.46101",
    "logType": "Rerouting",
    "eventType": "Rerouting Option Previewed",
    "logMessages": [
      "Rerouting option previewed for Uav Echo ",
      "Path start time: 10/19/2022 17:46:57.964518",
      "Previewed route is good"
    ]
  },
  {
    "timestamp": "10/19/2022 17:47:18.050152",
    "simulationTimeStamp": "30.4781",
    "logType": "Uav",
    "eventType": "ConditionChanged",
    "logMessages": [
      "Uav Alfa condition changed to Enabled"
    ]
  },
  {
    "timestamp": "10/19/2022 17:47:18.050152",
    "simulationTimeStamp": "30.4781",
    "logType": "Uav",
    "eventType": "ConditionChanged",
    "logMessages": [
      "Uav Bravo condition changed to Hidden"
    ]
  },
  {
    "timestamp": "10/19/2022 17:47:18.050152",
    "simulationTimeStamp": "30.4781",
    "logType": "Uav",
    "eventType": "ConditionChanged",
    "logMessages": [
      "Uav Charlie condition changed to Hidden"
    ]
  },
  {
    "timestamp": "10/19/2022 17:47:18.050152",
    "simulationTimeStamp": "30.4781",
    "logType": "Uav",
    "eventType": "ConditionChanged",
    "logMessages": [
      "Uav Delta condition changed to Hidden"
    ]
  },
  {
    "timestamp": "10/19/2022 17:47:18.050152",
    "simulationTimeStamp": "30.4781",
    "logType": "Uav",
    "eventType": "ConditionChanged",
    "logMessages": [
      "Uav Echo condition changed to Hidden"
    ]
  },
  {
    "timestamp": "10/19/2022 17:47:18.050152",
    "simulationTimeStamp": "30.4781",
    "logType": "Uav",
    "eventType": "ConditionChanged",
    "logMessages": [
      "Uav Frank condition changed to Hidden"
    ]
  },
  {
    "timestamp": "10/19/2022 17:47:18.051152",
    "simulationTimeStamp": "30.4781",
    "logType": "Uav",
    "eventType": "ConditionChanged",
    "logMessages": [
      "Uav Golf condition changed to Enabled"
    ]
  },
  {
    "timestamp": "10/19/2022 17:47:18.051152",
    "simulationTimeStamp": "30.4781",
    "logType": "Uav",
    "eventType": "ConditionChanged",
    "logMessages": [
      "Uav Hotel condition changed to Hidden"
    ]
  },
  {
    "timestamp": "10/19/2022 17:47:18.051152",
    "simulationTimeStamp": "30.4781",
    "logType": "Uav",
    "eventType": "ConditionChanged",
    "logMessages": [
      "Uav India condition changed to Enabled"
    ]
  },
  {
    "timestamp": "10/19/2022 17:47:18.051152",
    "simulationTimeStamp": "30.4781",
    "logType": "Uav",
    "eventType": "ConditionChanged",
    "logMessages": [
      "Uav John condition changed to Enabled"
    ]
  },
  {
    "timestamp": "10/19/2022 17:47:18.051152",
    "simulationTimeStamp": "30.4781",
    "logType": "Uav",
    "eventType": "ConditionChanged",
    "logMessages": [
      "Uav Kilo condition changed to Hidden"
    ]
  },
  {
    "timestamp": "10/19/2022 17:47:18.051152",
    "simulationTimeStamp": "30.4781",
    "logType": "Uav",
    "eventType": "ConditionChanged",
    "logMessages": [
      "Uav Lima condition changed to Hidden"
    ]
  },
  {
    "timestamp": "10/19/2022 17:47:18.051152",
    "simulationTimeStamp": "30.4781",
    "logType": "Uav",
    "eventType": "ConditionChanged",
    "logMessages": [
      "Uav Mike condition changed to Hidden"
    ]
  },
  {
    "timestamp": "10/19/2022 17:47:18.051152",
    "simulationTimeStamp": "30.4781",
    "logType": "Uav",
    "eventType": "ConditionChanged",
    "logMessages": [
      "Uav Nectar condition changed to Hidden"
    ]
  },
  {
    "timestamp": "10/19/2022 17:47:18.051152",
    "simulationTimeStamp": "30.4781",
    "logType": "Uav",
    "eventType": "ConditionChanged",
    "logMessages": [
      "Uav Oscar condition changed to Hidden"
    ]
  },
  {
    "timestamp": "10/19/2022 17:47:18.052152",
    "simulationTimeStamp": "30.4781",
    "logType": "Uav",
    "eventType": "ConditionChanged",
    "logMessages": [
      "Uav Papa condition changed to Hidden"
    ]
  },
  {
    "timestamp": "10/19/2022 17:47:19.977696",
    "simulationTimeStamp": "31.4624",
    "logType": "Prompts",
    "eventType": "PromptMessageSent",
    "logMessages": [
      "Prompt Message: Which UAV/s had a bad projected route?",
      "Allowed Response Time: 0.0",
      "Correct Response Options:  | #10",
      "Wrong Response Options:  | #0 | #1 | #2 | #3 | #4 | #5 | #6 | #7 | #8 | #9 | #11 | #12 | #13 | #14 | #15"
    ]
  }
]