[
  {
    "timestamp": "10/30/2022 10:54:28.505411",
    "simulationTimeStamp": "75.74562",
    "logType": "Uav",
    "eventType": "Created",
    "logMessages": [
      "Uav Alfa created"
    ],
    "logGenerator": "None"
  },
  {
    "timestamp": "10/30/2022 10:54:28.513429",
    "simulationTimeStamp": "75.74562",
    "logType": "Uav",
    "eventType": "Created",
    "logMessages": [
      "Uav Bravo created"
    ],
    "logGenerator": "None"
  },
  {
    "timestamp": "10/30/2022 10:54:28.515430",
    "simulationTimeStamp": "75.74562",
    "logType": "Uav",
    "eventType": "Created",
    "logMessages": [
      "Uav Charlie created"
    ],
    "logGenerator": "None"
  },
  {
    "timestamp": "10/30/2022 10:54:28.518431",
    "simulationTimeStamp": "75.74562",
    "logType": "Uav",
    "eventType": "Created",
    "logMessages": [
      "Uav Delta created"
    ],
    "logGenerator": "None"
  },
  {
    "timestamp": "10/30/2022 10:54:28.520431",
    "simulationTimeStamp": "75.74562",
    "logType": "Uav",
    "eventType": "Created",
    "logMessages": [
      "Uav Echo created"
    ],
    "logGenerator": "None"
  },
  {
    "timestamp": "10/30/2022 10:54:28.522919",
    "simulationTimeStamp": "75.74562",
    "logType": "Uav",
    "eventType": "Created",
    "logMessages": [
      "Uav Frank created"
    ],
    "logGenerator": "None"
  },
  {
    "timestamp": "10/30/2022 10:54:28.525919",
    "simulationTimeStamp": "75.74562",
    "logType": "Uav",
    "eventType": "Created",
    "logMessages": [
      "Uav Golf created"
    ],
    "logGenerator": "None"
  },
  {
    "timestamp": "10/30/2022 10:54:28.527920",
    "simulationTimeStamp": "75.74562",
    "logType": "Uav",
    "eventType": "Created",
    "logMessages": [
      "Uav Hotel created"
    ],
    "logGenerator": "None"
  },
  {
    "timestamp": "10/30/2022 10:54:28.529921",
    "simulationTimeStamp": "75.74562",
    "logType": "Uav",
    "eventType": "Created",
    "logMessages": [
      "Uav India created"
    ],
    "logGenerator": "None"
  },
  {
    "timestamp": "10/30/2022 10:54:28.532453",
    "simulationTimeStamp": "75.74562",
    "logType": "Uav",
    "eventType": "Created",
    "logMessages": [
      "Uav John created"
    ],
    "logGenerator": "None"
  },
  {
    "timestamp": "10/30/2022 10:54:28.535455",
    "simulationTimeStamp": "75.74562",
    "logType": "Uav",
    "eventType": "Created",
    "logMessages": [
      "Uav Kilo created"
    ],
    "logGenerator": "None"
  },
  {
    "timestamp": "10/30/2022 10:54:28.537455",
    "simulationTimeStamp": "75.74562",
    "logType": "Uav",
    "eventType": "Created",
    "logMessages": [
      "Uav Lima created"
    ],
    "logGenerator": "None"
  },
  {
    "timestamp": "10/30/2022 10:54:28.540152",
    "simulationTimeStamp": "75.74562",
    "logType": "Uav",
    "eventType": "Created",
    "logMessages": [
      "Uav Mike created"
    ],
    "logGenerator": "None"
  },
  {
    "timestamp": "10/30/2022 10:54:28.541966",
    "simulationTimeStamp": "75.74562",
    "logType": "Uav",
    "eventType": "Created",
    "logMessages": [
      "Uav Nectar created"
    ],
    "logGenerator": "None"
  },
  {
    "timestamp": "10/30/2022 10:54:28.544967",
    "simulationTimeStamp": "75.74562",
    "logType": "Uav",
    "eventType": "Created",
    "logMessages": [
      "Uav Oscar created"
    ],
    "logGenerator": "None"
  },
  {
    "timestamp": "10/30/2022 10:54:28.547026",
    "simulationTimeStamp": "75.74562",
    "logType": "Uav",
    "eventType": "Created",
    "logMessages": [
      "Uav Papa created"
    ],
    "logGenerator": "None"
  },
  {
    "timestamp": "10/30/2022 10:54:33.397759",
    "simulationTimeStamp": "80.65676",
    "logType": "Uav",
    "eventType": "ConditionChanged",
    "logMessages": [
      "Uav Alfa condition changed to Hidden"
    ],
    "logGenerator": "None"
  },
  {
    "timestamp": "10/30/2022 10:54:33.404762",
    "simulationTimeStamp": "80.65676",
    "logType": "Uav",
    "eventType": "ConditionChanged",
    "logMessages": [
      "Uav Bravo condition changed to Hidden"
    ],
    "logGenerator": "None"
  },
  {
    "timestamp": "10/30/2022 10:54:33.405762",
    "simulationTimeStamp": "80.65676",
    "logType": "Uav",
    "eventType": "ConditionChanged",
    "logMessages": [
      "Uav Charlie condition changed to Hidden"
    ],
    "logGenerator": "None"
  },
  {
    "timestamp": "10/30/2022 10:54:33.405762",
    "simulationTimeStamp": "80.65676",
    "logType": "Uav",
    "eventType": "ConditionChanged",
    "logMessages": [
      "Uav Delta condition changed to Hidden"
    ],
    "logGenerator": "None"
  },
  {
    "timestamp": "10/30/2022 10:54:33.406762",
    "simulationTimeStamp": "80.65676",
    "logType": "Uav",
    "eventType": "ConditionChanged",
    "logMessages": [
      "Uav Echo condition changed to Enabled"
    ],
    "logGenerator": "None"
  },
  {
    "timestamp": "10/30/2022 10:54:33.407762",
    "simulationTimeStamp": "80.65676",
    "logType": "Uav",
    "eventType": "ConditionChanged",
    "logMessages": [
      "Uav Frank condition changed to Hidden"
    ],
    "logGenerator": "None"
  },
  {
    "timestamp": "10/30/2022 10:54:33.407762",
    "simulationTimeStamp": "80.65676",
    "logType": "Uav",
    "eventType": "ConditionChanged",
    "logMessages": [
      "Uav Golf condition changed to Hidden"
    ],
    "logGenerator": "None"
  },
  {
    "timestamp": "10/30/2022 10:54:33.407762",
    "simulationTimeStamp": "80.65676",
    "logType": "Uav",
    "eventType": "ConditionChanged",
    "logMessages": [
      "Uav Hotel condition changed to Hidden"
    ],
    "logGenerator": "None"
  },
  {
    "timestamp": "10/30/2022 10:54:33.407762",
    "simulationTimeStamp": "80.65676",
    "logType": "Uav",
    "eventType": "ConditionChanged",
    "logMessages": [
      "Uav India condition changed to Hidden"
    ],
    "logGenerator": "None"
  },
  {
    "timestamp": "10/30/2022 10:54:33.407762",
    "simulationTimeStamp": "80.65676",
    "logType": "Uav",
    "eventType": "ConditionChanged",
    "logMessages": [
      "Uav John condition changed to Enabled"
    ],
    "logGenerator": "None"
  },
  {
    "timestamp": "10/30/2022 10:54:33.408763",
    "simulationTimeStamp": "80.65676",
    "logType": "Uav",
    "eventType": "ConditionChanged",
    "logMessages": [
      "Uav Kilo condition changed to Hidden"
    ],
    "logGenerator": "None"
  },
  {
    "timestamp": "10/30/2022 10:54:33.408763",
    "simulationTimeStamp": "80.65676",
    "logType": "Uav",
    "eventType": "ConditionChanged",
    "logMessages": [
      "Uav Lima condition changed to Hidden"
    ],
    "logGenerator": "None"
  },
  {
    "timestamp": "10/30/2022 10:54:33.408763",
    "simulationTimeStamp": "80.65676",
    "logType": "Uav",
    "eventType": "ConditionChanged",
    "logMessages": [
      "Uav Mike condition changed to Hidden"
    ],
    "logGenerator": "None"
  },
  {
    "timestamp": "10/30/2022 10:54:33.408763",
    "simulationTimeStamp": "80.65676",
    "logType": "Uav",
    "eventType": "ConditionChanged",
    "logMessages": [
      "Uav Nectar condition changed to Hidden"
    ],
    "logGenerator": "None"
  },
  {
    "timestamp": "10/30/2022 10:54:33.408763",
    "simulationTimeStamp": "80.65676",
    "logType": "Uav",
    "eventType": "ConditionChanged",
    "logMessages": [
      "Uav Oscar condition changed to Hidden"
    ],
    "logGenerator": "None"
  },
  {
    "timestamp": "10/30/2022 10:54:33.409763",
    "simulationTimeStamp": "80.65676",
    "logType": "Uav",
    "eventType": "ConditionChanged",
    "logMessages": [
      "Uav Papa condition changed to Enabled"
    ],
    "logGenerator": "None"
  },
  {
    "timestamp": "10/30/2022 10:54:33.414610",
    "simulationTimeStamp": "80.65676",
    "logType": "Prompts",
    "eventType": "PromptMessageSent",
    "logMessages": [
      "Prompt Message: beginning Mission",
      "Allowed Response Time: 0.0"
    ],
    "logGenerator": "None"
  },
  {
    "timestamp": "10/30/2022 10:54:47.405752",
    "simulationTimeStamp": "94.67043",
    "logType": "Uav",
    "eventType": "ConditionChanged",
    "logMessages": [
      "Uav Alfa condition changed to Enabled"
    ],
    "logGenerator": "None"
  },
  {
    "timestamp": "10/30/2022 10:54:47.405752",
    "simulationTimeStamp": "94.67043",
    "logType": "Uav",
    "eventType": "ConditionChanged",
    "logMessages": [
      "Uav Bravo condition changed to Hidden"
    ],
    "logGenerator": "None"
  },
  {
    "timestamp": "10/30/2022 10:54:47.406752",
    "simulationTimeStamp": "94.67043",
    "logType": "Uav",
    "eventType": "ConditionChanged",
    "logMessages": [
      "Uav Charlie condition changed to Hidden"
    ],
    "logGenerator": "None"
  },
  {
    "timestamp": "10/30/2022 10:54:47.406752",
    "simulationTimeStamp": "94.67043",
    "logType": "Uav",
    "eventType": "ConditionChanged",
    "logMessages": [
      "Uav Delta condition changed to Hidden"
    ],
    "logGenerator": "None"
  },
  {
    "timestamp": "10/30/2022 10:54:47.406752",
    "simulationTimeStamp": "94.67043",
    "logType": "Uav",
    "eventType": "ConditionChanged",
    "logMessages": [
      "Uav Echo condition changed to Hidden"
    ],
    "logGenerator": "None"
  },
  {
    "timestamp": "10/30/2022 10:54:47.406752",
    "simulationTimeStamp": "94.67043",
    "logType": "Uav",
    "eventType": "ConditionChanged",
    "logMessages": [
      "Uav Frank condition changed to Hidden"
    ],
    "logGenerator": "None"
  },
  {
    "timestamp": "10/30/2022 10:54:47.407754",
    "simulationTimeStamp": "94.67043",
    "logType": "Uav",
    "eventType": "ConditionChanged",
    "logMessages": [
      "Uav Golf condition changed to Enabled"
    ],
    "logGenerator": "None"
  },
  {
    "timestamp": "10/30/2022 10:54:47.407754",
    "simulationTimeStamp": "94.67043",
    "logType": "Uav",
    "eventType": "ConditionChanged",
    "logMessages": [
      "Uav Hotel condition changed to Hidden"
    ],
    "logGenerator": "None"
  },
  {
    "timestamp": "10/30/2022 10:54:47.407754",
    "simulationTimeStamp": "94.67043",
    "logType": "Uav",
    "eventType": "ConditionChanged",
    "logMessages": [
      "Uav India condition changed to Enabled"
    ],
    "logGenerator": "None"
  },
  {
    "timestamp": "10/30/2022 10:54:47.407754",
    "simulationTimeStamp": "94.67043",
    "logType": "Uav",
    "eventType": "ConditionChanged",
    "logMessages": [
      "Uav John condition changed to Enabled"
    ],
    "logGenerator": "None"
  },
  {
    "timestamp": "10/30/2022 10:54:47.407754",
    "simulationTimeStamp": "94.67043",
    "logType": "Uav",
    "eventType": "ConditionChanged",
    "logMessages": [
      "Uav Kilo condition changed to Hidden"
    ],
    "logGenerator": "None"
  },
  {
    "timestamp": "10/30/2022 10:54:47.407754",
    "simulationTimeStamp": "94.67043",
    "logType": "Uav",
    "eventType": "ConditionChanged",
    "logMessages": [
      "Uav Lima condition changed to Hidden"
    ],
    "logGenerator": "None"
  },
  {
    "timestamp": "10/30/2022 10:54:47.407754",
    "simulationTimeStamp": "94.67043",
    "logType": "Uav",
    "eventType": "ConditionChanged",
    "logMessages": [
      "Uav Mike condition changed to Hidden"
    ],
    "logGenerator": "None"
  },
  {
    "timestamp": "10/30/2022 10:54:47.408753",
    "simulationTimeStamp": "94.67043",
    "logType": "Uav",
    "eventType": "ConditionChanged",
    "logMessages": [
      "Uav Nectar condition changed to Hidden"
    ],
    "logGenerator": "None"
  },
  {
    "timestamp": "10/30/2022 10:54:47.408753",
    "simulationTimeStamp": "94.67043",
    "logType": "Uav",
    "eventType": "ConditionChanged",
    "logMessages": [
      "Uav Oscar condition changed to Hidden"
    ],
    "logGenerator": "None"
  },
  {
    "timestamp": "10/30/2022 10:54:47.408753",
    "simulationTimeStamp": "94.67043",
    "logType": "Uav",
    "eventType": "ConditionChanged",
    "logMessages": [
      "Uav Papa condition changed to Hidden"
    ],
    "logGenerator": "None"
  },
  {
    "timestamp": "10/30/2022 10:54:48.392496",
    "simulationTimeStamp": "95.64984",
    "logType": "Prompts",
    "eventType": "PromptMessageSent",
    "logMessages": [
      "Prompt Message: Which UAV/s had a bad projected route?",
      "Allowed Response Time: 0.0",
      "Correct Response Options:  | #10",
      "Wrong Response Options:  | #0 | #1 | #2 | #3 | #4 | #5 | #6 | #7 | #8 | #9 | #11 | #12 | #13 | #14 | #15"
    ],
    "logGenerator": "None"
  }
]