[
  {
    "timestamp": "10/18/2022 22:09:53.729064",
    "simulationTimeStamp": "20.65223",
    "logType": "Uav",
    "eventType": "Created",
    "logMessages": [
      "Uav Alfa created"
    ]
  },
  {
    "timestamp": "10/18/2022 22:09:53.737306",
    "simulationTimeStamp": "20.65223",
    "logType": "Uav",
    "eventType": "Created",
    "logMessages": [
      "Uav Bravo created"
    ]
  },
  {
    "timestamp": "10/18/2022 22:09:53.740307",
    "simulationTimeStamp": "20.65223",
    "logType": "Uav",
    "eventType": "Created",
    "logMessages": [
      "Uav Charlie created"
    ]
  },
  {
    "timestamp": "10/18/2022 22:09:53.743307",
    "simulationTimeStamp": "20.65223",
    "logType": "Uav",
    "eventType": "Created",
    "logMessages": [
      "Uav Delta created"
    ]
  },
  {
    "timestamp": "10/18/2022 22:09:53.746308",
    "simulationTimeStamp": "20.65223",
    "logType": "Uav",
    "eventType": "Created",
    "logMessages": [
      "Uav Echo created"
    ]
  },
  {
    "timestamp": "10/18/2022 22:09:53.749310",
    "simulationTimeStamp": "20.65223",
    "logType": "Uav",
    "eventType": "Created",
    "logMessages": [
      "Uav Frank created"
    ]
  },
  {
    "timestamp": "10/18/2022 22:09:53.752725",
    "simulationTimeStamp": "20.65223",
    "logType": "Uav",
    "eventType": "Created",
    "logMessages": [
      "Uav Golf created"
    ]
  },
  {
    "timestamp": "10/18/2022 22:09:53.755311",
    "simulationTimeStamp": "20.65223",
    "logType": "Uav",
    "eventType": "Created",
    "logMessages": [
      "Uav Hotel created"
    ]
  },
  {
    "timestamp": "10/18/2022 22:09:53.757336",
    "simulationTimeStamp": "20.65223",
    "logType": "Uav",
    "eventType": "Created",
    "logMessages": [
      "Uav India created"
    ]
  },
  {
    "timestamp": "10/18/2022 22:09:53.760378",
    "simulationTimeStamp": "20.65223",
    "logType": "Uav",
    "eventType": "Created",
    "logMessages": [
      "Uav John created"
    ]
  },
  {
    "timestamp": "10/18/2022 22:09:53.763378",
    "simulationTimeStamp": "20.65223",
    "logType": "Uav",
    "eventType": "Created",
    "logMessages": [
      "Uav Kilo created"
    ]
  },
  {
    "timestamp": "10/18/2022 22:09:53.766381",
    "simulationTimeStamp": "20.65223",
    "logType": "Uav",
    "eventType": "Created",
    "logMessages": [
      "Uav Lima created"
    ]
  },
  {
    "timestamp": "10/18/2022 22:09:53.769380",
    "simulationTimeStamp": "20.65223",
    "logType": "Uav",
    "eventType": "Created",
    "logMessages": [
      "Uav Mike created"
    ]
  },
  {
    "timestamp": "10/18/2022 22:09:53.772381",
    "simulationTimeStamp": "20.65223",
    "logType": "Uav",
    "eventType": "Created",
    "logMessages": [
      "Uav Nectar created"
    ]
  },
  {
    "timestamp": "10/18/2022 22:09:53.775382",
    "simulationTimeStamp": "20.65223",
    "logType": "Uav",
    "eventType": "Created",
    "logMessages": [
      "Uav Oscar created"
    ]
  },
  {
    "timestamp": "10/18/2022 22:09:53.778383",
    "simulationTimeStamp": "20.65223",
    "logType": "Uav",
    "eventType": "Created",
    "logMessages": [
      "Uav Papa created"
    ]
  },
  {
    "timestamp": "10/18/2022 22:09:58.620010",
    "simulationTimeStamp": "25.55547",
    "logType": "Uav",
    "eventType": "ConditionChanged",
    "logMessages": [
      "Uav Alfa condition changed to Hidden"
    ]
  },
  {
    "timestamp": "10/18/2022 22:09:58.625042",
    "simulationTimeStamp": "25.55547",
    "logType": "Uav",
    "eventType": "ConditionChanged",
    "logMessages": [
      "Uav Bravo condition changed to Hidden"
    ]
  },
  {
    "timestamp": "10/18/2022 22:09:58.625042",
    "simulationTimeStamp": "25.55547",
    "logType": "Uav",
    "eventType": "ConditionChanged",
    "logMessages": [
      "Uav Charlie condition changed to Hidden"
    ]
  },
  {
    "timestamp": "10/18/2022 22:09:58.626044",
    "simulationTimeStamp": "25.55547",
    "logType": "Uav",
    "eventType": "ConditionChanged",
    "logMessages": [
      "Uav Delta condition changed to Hidden"
    ]
  },
  {
    "timestamp": "10/18/2022 22:09:58.627044",
    "simulationTimeStamp": "25.55547",
    "logType": "Uav",
    "eventType": "ConditionChanged",
    "logMessages": [
      "Uav Echo condition changed to Enabled"
    ]
  },
  {
    "timestamp": "10/18/2022 22:09:58.627044",
    "simulationTimeStamp": "25.55547",
    "logType": "Uav",
    "eventType": "ConditionChanged",
    "logMessages": [
      "Uav Frank condition changed to Hidden"
    ]
  },
  {
    "timestamp": "10/18/2022 22:09:58.627044",
    "simulationTimeStamp": "25.55547",
    "logType": "Uav",
    "eventType": "ConditionChanged",
    "logMessages": [
      "Uav Golf condition changed to Hidden"
    ]
  },
  {
    "timestamp": "10/18/2022 22:09:58.627044",
    "simulationTimeStamp": "25.55547",
    "logType": "Uav",
    "eventType": "ConditionChanged",
    "logMessages": [
      "Uav Hotel condition changed to Hidden"
    ]
  },
  {
    "timestamp": "10/18/2022 22:09:58.627044",
    "simulationTimeStamp": "25.55547",
    "logType": "Uav",
    "eventType": "ConditionChanged",
    "logMessages": [
      "Uav India condition changed to Hidden"
    ]
  },
  {
    "timestamp": "10/18/2022 22:09:58.628045",
    "simulationTimeStamp": "25.55547",
    "logType": "Uav",
    "eventType": "ConditionChanged",
    "logMessages": [
      "Uav John condition changed to Enabled"
    ]
  },
  {
    "timestamp": "10/18/2022 22:09:58.628045",
    "simulationTimeStamp": "25.55547",
    "logType": "Uav",
    "eventType": "ConditionChanged",
    "logMessages": [
      "Uav Kilo condition changed to Hidden"
    ]
  },
  {
    "timestamp": "10/18/2022 22:09:58.628045",
    "simulationTimeStamp": "25.55547",
    "logType": "Uav",
    "eventType": "ConditionChanged",
    "logMessages": [
      "Uav Lima condition changed to Hidden"
    ]
  },
  {
    "timestamp": "10/18/2022 22:09:58.628045",
    "simulationTimeStamp": "25.55547",
    "logType": "Uav",
    "eventType": "ConditionChanged",
    "logMessages": [
      "Uav Mike condition changed to Hidden"
    ]
  },
  {
    "timestamp": "10/18/2022 22:09:58.628045",
    "simulationTimeStamp": "25.55547",
    "logType": "Uav",
    "eventType": "ConditionChanged",
    "logMessages": [
      "Uav Nectar condition changed to Hidden"
    ]
  },
  {
    "timestamp": "10/18/2022 22:09:58.629045",
    "simulationTimeStamp": "25.55547",
    "logType": "Uav",
    "eventType": "ConditionChanged",
    "logMessages": [
      "Uav Oscar condition changed to Hidden"
    ]
  },
  {
    "timestamp": "10/18/2022 22:09:58.629045",
    "simulationTimeStamp": "25.55547",
    "logType": "Uav",
    "eventType": "ConditionChanged",
    "logMessages": [
      "Uav Papa condition changed to Enabled"
    ]
  },
  {
    "timestamp": "10/18/2022 22:09:58.632045",
    "simulationTimeStamp": "25.55547",
    "logType": "Prompts",
    "eventType": "PromptMessageSent",
    "logMessages": [
      "Prompt Message: beginning Mission",
      "Allowed Response Time: 0.0"
    ]
  },
  {
    "timestamp": "10/18/2022 22:10:12.615358",
    "simulationTimeStamp": "39.55664",
    "logType": "Uav",
    "eventType": "ConditionChanged",
    "logMessages": [
      "Uav Alfa condition changed to Enabled"
    ]
  },
  {
    "timestamp": "10/18/2022 22:10:12.615358",
    "simulationTimeStamp": "39.55664",
    "logType": "Uav",
    "eventType": "ConditionChanged",
    "logMessages": [
      "Uav Bravo condition changed to Hidden"
    ]
  },
  {
    "timestamp": "10/18/2022 22:10:12.616357",
    "simulationTimeStamp": "39.55664",
    "logType": "Uav",
    "eventType": "ConditionChanged",
    "logMessages": [
      "Uav Charlie condition changed to Hidden"
    ]
  },
  {
    "timestamp": "10/18/2022 22:10:12.616357",
    "simulationTimeStamp": "39.55664",
    "logType": "Uav",
    "eventType": "ConditionChanged",
    "logMessages": [
      "Uav Delta condition changed to Hidden"
    ]
  },
  {
    "timestamp": "10/18/2022 22:10:12.616357",
    "simulationTimeStamp": "39.55664",
    "logType": "Uav",
    "eventType": "ConditionChanged",
    "logMessages": [
      "Uav Echo condition changed to Hidden"
    ]
  },
  {
    "timestamp": "10/18/2022 22:10:12.616357",
    "simulationTimeStamp": "39.55664",
    "logType": "Uav",
    "eventType": "ConditionChanged",
    "logMessages": [
      "Uav Frank condition changed to Hidden"
    ]
  },
  {
    "timestamp": "10/18/2022 22:10:12.617358",
    "simulationTimeStamp": "39.55664",
    "logType": "Uav",
    "eventType": "ConditionChanged",
    "logMessages": [
      "Uav Golf condition changed to Enabled"
    ]
  },
  {
    "timestamp": "10/18/2022 22:10:12.617358",
    "simulationTimeStamp": "39.55664",
    "logType": "Uav",
    "eventType": "ConditionChanged",
    "logMessages": [
      "Uav Hotel condition changed to Hidden"
    ]
  },
  {
    "timestamp": "10/18/2022 22:10:12.617358",
    "simulationTimeStamp": "39.55664",
    "logType": "Uav",
    "eventType": "ConditionChanged",
    "logMessages": [
      "Uav India condition changed to Enabled"
    ]
  },
  {
    "timestamp": "10/18/2022 22:10:12.617358",
    "simulationTimeStamp": "39.55664",
    "logType": "Uav",
    "eventType": "ConditionChanged",
    "logMessages": [
      "Uav John condition changed to Enabled"
    ]
  },
  {
    "timestamp": "10/18/2022 22:10:12.617358",
    "simulationTimeStamp": "39.55664",
    "logType": "Uav",
    "eventType": "ConditionChanged",
    "logMessages": [
      "Uav Kilo condition changed to Hidden"
    ]
  },
  {
    "timestamp": "10/18/2022 22:10:12.617358",
    "simulationTimeStamp": "39.55664",
    "logType": "Uav",
    "eventType": "ConditionChanged",
    "logMessages": [
      "Uav Lima condition changed to Hidden"
    ]
  },
  {
    "timestamp": "10/18/2022 22:10:12.617358",
    "simulationTimeStamp": "39.55664",
    "logType": "Uav",
    "eventType": "ConditionChanged",
    "logMessages": [
      "Uav Mike condition changed to Hidden"
    ]
  },
  {
    "timestamp": "10/18/2022 22:10:12.617358",
    "simulationTimeStamp": "39.55664",
    "logType": "Uav",
    "eventType": "ConditionChanged",
    "logMessages": [
      "Uav Nectar condition changed to Hidden"
    ]
  },
  {
    "timestamp": "10/18/2022 22:10:12.617358",
    "simulationTimeStamp": "39.55664",
    "logType": "Uav",
    "eventType": "ConditionChanged",
    "logMessages": [
      "Uav Oscar condition changed to Hidden"
    ]
  },
  {
    "timestamp": "10/18/2022 22:10:12.618358",
    "simulationTimeStamp": "39.55664",
    "logType": "Uav",
    "eventType": "ConditionChanged",
    "logMessages": [
      "Uav Papa condition changed to Hidden"
    ]
  },
  {
    "timestamp": "10/18/2022 22:10:13.624983",
    "simulationTimeStamp": "40.55903",
    "logType": "Prompts",
    "eventType": "PromptMessageSent",
    "logMessages": [
      "Prompt Message: Which UAV/s had a bad projected route?",
      "Allowed Response Time: 0.0",
      "Correct Response Options:  | #10",
      "Wrong Response Options:  | #0 | #1 | #2 | #3 | #4 | #5 | #6 | #7 | #8 | #9 | #11 | #12 | #13 | #14 | #15"
    ]
  },
  {
    "timestamp": "10/18/2022 22:10:20.618927",
    "simulationTimeStamp": "47.55767",
    "logType": "Prompts",
    "eventType": "PromptMessageSent",
    "logMessages": [
      "Prompt Message: Detecting UAV 6 flying away from NFZ?",
      "Allowed Response Time: 10.0",
      "Correct Response Options:  | Confirm",
      "Wrong Response Options:  | Deny"
    ]
  },
  {
    "timestamp": "10/18/2022 22:10:26.616908",
    "simulationTimeStamp": "53.55786",
    "logType": "Uav",
    "eventType": "ConditionChanged",
    "logMessages": [
      "Uav Alfa condition changed to Hidden"
    ]
  },
  {
    "timestamp": "10/18/2022 22:10:26.616908",
    "simulationTimeStamp": "53.55786",
    "logType": "Uav",
    "eventType": "ConditionChanged",
    "logMessages": [
      "Uav Bravo condition changed to Hidden"
    ]
  },
  {
    "timestamp": "10/18/2022 22:10:26.616908",
    "simulationTimeStamp": "53.55786",
    "logType": "Uav",
    "eventType": "ConditionChanged",
    "logMessages": [
      "Uav Charlie condition changed to Hidden"
    ]
  },
  {
    "timestamp": "10/18/2022 22:10:26.616908",
    "simulationTimeStamp": "53.55786",
    "logType": "Uav",
    "eventType": "ConditionChanged",
    "logMessages": [
      "Uav Delta condition changed to Enabled"
    ]
  },
  {
    "timestamp": "10/18/2022 22:10:26.616908",
    "simulationTimeStamp": "53.55786",
    "logType": "Uav",
    "eventType": "ConditionChanged",
    "logMessages": [
      "Uav Echo condition changed to Hidden"
    ]
  },
  {
    "timestamp": "10/18/2022 22:10:26.616908",
    "simulationTimeStamp": "53.55786",
    "logType": "Uav",
    "eventType": "ConditionChanged",
    "logMessages": [
      "Uav Frank condition changed to Enabled"
    ]
  },
  {
    "timestamp": "10/18/2022 22:10:26.617908",
    "simulationTimeStamp": "53.55786",
    "logType": "Uav",
    "eventType": "ConditionChanged",
    "logMessages": [
      "Uav Golf condition changed to Hidden"
    ]
  },
  {
    "timestamp": "10/18/2022 22:10:26.617908",
    "simulationTimeStamp": "53.55786",
    "logType": "Uav",
    "eventType": "ConditionChanged",
    "logMessages": [
      "Uav Hotel condition changed to Enabled"
    ]
  },
  {
    "timestamp": "10/18/2022 22:10:26.617908",
    "simulationTimeStamp": "53.55786",
    "logType": "Uav",
    "eventType": "ConditionChanged",
    "logMessages": [
      "Uav India condition changed to Hidden"
    ]
  },
  {
    "timestamp": "10/18/2022 22:10:26.617908",
    "simulationTimeStamp": "53.55786",
    "logType": "Uav",
    "eventType": "ConditionChanged",
    "logMessages": [
      "Uav John condition changed to Hidden"
    ]
  },
  {
    "timestamp": "10/18/2022 22:10:26.617908",
    "simulationTimeStamp": "53.55786",
    "logType": "Uav",
    "eventType": "ConditionChanged",
    "logMessages": [
      "Uav Kilo condition changed to Hidden"
    ]
  },
  {
    "timestamp": "10/18/2022 22:10:26.617908",
    "simulationTimeStamp": "53.55786",
    "logType": "Uav",
    "eventType": "ConditionChanged",
    "logMessages": [
      "Uav Lima condition changed to Hidden"
    ]
  },
  {
    "timestamp": "10/18/2022 22:10:26.617908",
    "simulationTimeStamp": "53.55786",
    "logType": "Uav",
    "eventType": "ConditionChanged",
    "logMessages": [
      "Uav Mike condition changed to Enabled"
    ]
  },
  {
    "timestamp": "10/18/2022 22:10:26.617908",
    "simulationTimeStamp": "53.55786",
    "logType": "Uav",
    "eventType": "ConditionChanged",
    "logMessages": [
      "Uav Nectar condition changed to Hidden"
    ]
  },
  {
    "timestamp": "10/18/2022 22:10:26.618909",
    "simulationTimeStamp": "53.55786",
    "logType": "Uav",
    "eventType": "ConditionChanged",
    "logMessages": [
      "Uav Oscar condition changed to Hidden"
    ]
  },
  {
    "timestamp": "10/18/2022 22:10:26.618909",
    "simulationTimeStamp": "53.55786",
    "logType": "Uav",
    "eventType": "ConditionChanged",
    "logMessages": [
      "Uav Papa condition changed to Hidden"
    ]
  }
]