[
  {
    "timestamp": "11/12/2022 11:47:54.375501",
    "simulationTimeStamp": "38.09931",
    "logType": "Uav",
    "eventType": "Created",
    "logMessages": [
      "Uav Alfa created"
    ],
    "logGenerator": "None"
  },
  {
    "timestamp": "11/12/2022 11:47:54.383903",
    "simulationTimeStamp": "38.09931",
    "logType": "Uav",
    "eventType": "Created",
    "logMessages": [
      "Uav Bravo created"
    ],
    "logGenerator": "None"
  },
  {
    "timestamp": "11/12/2022 11:47:54.386957",
    "simulationTimeStamp": "38.09931",
    "logType": "Uav",
    "eventType": "Created",
    "logMessages": [
      "Uav Charlie created"
    ],
    "logGenerator": "None"
  },
  {
    "timestamp": "11/12/2022 11:47:54.388964",
    "simulationTimeStamp": "38.09931",
    "logType": "Uav",
    "eventType": "Created",
    "logMessages": [
      "Uav Delta created"
    ],
    "logGenerator": "None"
  },
  {
    "timestamp": "11/12/2022 11:47:54.391963",
    "simulationTimeStamp": "38.09931",
    "logType": "Uav",
    "eventType": "Created",
    "logMessages": [
      "Uav Echo created"
    ],
    "logGenerator": "None"
  },
  {
    "timestamp": "11/12/2022 11:47:54.393964",
    "simulationTimeStamp": "38.09931",
    "logType": "Uav",
    "eventType": "Created",
    "logMessages": [
      "Uav Frank created"
    ],
    "logGenerator": "None"
  },
  {
    "timestamp": "11/12/2022 11:47:54.396021",
    "simulationTimeStamp": "38.09931",
    "logType": "Uav",
    "eventType": "Created",
    "logMessages": [
      "Uav Golf created"
    ],
    "logGenerator": "None"
  },
  {
    "timestamp": "11/12/2022 11:47:54.399228",
    "simulationTimeStamp": "38.09931",
    "logType": "Uav",
    "eventType": "Created",
    "logMessages": [
      "Uav Hotel created"
    ],
    "logGenerator": "None"
  },
  {
    "timestamp": "11/12/2022 11:47:54.401229",
    "simulationTimeStamp": "38.09931",
    "logType": "Uav",
    "eventType": "Created",
    "logMessages": [
      "Uav India created"
    ],
    "logGenerator": "None"
  },
  {
    "timestamp": "11/12/2022 11:47:54.404228",
    "simulationTimeStamp": "38.09931",
    "logType": "Uav",
    "eventType": "Created",
    "logMessages": [
      "Uav John created"
    ],
    "logGenerator": "None"
  },
  {
    "timestamp": "11/12/2022 11:47:54.406229",
    "simulationTimeStamp": "38.09931",
    "logType": "Uav",
    "eventType": "Created",
    "logMessages": [
      "Uav Kilo created"
    ],
    "logGenerator": "None"
  },
  {
    "timestamp": "11/12/2022 11:47:54.408740",
    "simulationTimeStamp": "38.09931",
    "logType": "Uav",
    "eventType": "Created",
    "logMessages": [
      "Uav Lima created"
    ],
    "logGenerator": "None"
  },
  {
    "timestamp": "11/12/2022 11:47:54.410740",
    "simulationTimeStamp": "38.09931",
    "logType": "Uav",
    "eventType": "Created",
    "logMessages": [
      "Uav Mike created"
    ],
    "logGenerator": "None"
  },
  {
    "timestamp": "11/12/2022 11:47:54.413741",
    "simulationTimeStamp": "38.09931",
    "logType": "Uav",
    "eventType": "Created",
    "logMessages": [
      "Uav Nectar created"
    ],
    "logGenerator": "None"
  },
  {
    "timestamp": "11/12/2022 11:47:54.415739",
    "simulationTimeStamp": "38.09931",
    "logType": "Uav",
    "eventType": "Created",
    "logMessages": [
      "Uav Oscar created"
    ],
    "logGenerator": "None"
  },
  {
    "timestamp": "11/12/2022 11:47:54.418760",
    "simulationTimeStamp": "38.09931",
    "logType": "Uav",
    "eventType": "Created",
    "logMessages": [
      "Uav Papa created"
    ],
    "logGenerator": "None"
  },
  {
    "timestamp": "11/12/2022 11:47:59.267549",
    "simulationTimeStamp": "43.00049",
    "logType": "Uav",
    "eventType": "ConditionChanged",
    "logMessages": [
      "Uav Alfa condition changed to Hidden"
    ],
    "logGenerator": "None"
  },
  {
    "timestamp": "11/12/2022 11:47:59.272996",
    "simulationTimeStamp": "43.00049",
    "logType": "Uav",
    "eventType": "ConditionChanged",
    "logMessages": [
      "Uav Bravo condition changed to Hidden"
    ],
    "logGenerator": "None"
  },
  {
    "timestamp": "11/12/2022 11:47:59.272996",
    "simulationTimeStamp": "43.00049",
    "logType": "Uav",
    "eventType": "ConditionChanged",
    "logMessages": [
      "Uav Charlie condition changed to Hidden"
    ],
    "logGenerator": "None"
  },
  {
    "timestamp": "11/12/2022 11:47:59.274151",
    "simulationTimeStamp": "43.00049",
    "logType": "Uav",
    "eventType": "ConditionChanged",
    "logMessages": [
      "Uav Delta condition changed to Hidden"
    ],
    "logGenerator": "None"
  },
  {
    "timestamp": "11/12/2022 11:47:59.274151",
    "simulationTimeStamp": "43.00049",
    "logType": "Uav",
    "eventType": "ConditionChanged",
    "logMessages": [
      "Uav Echo condition changed to Enabled"
    ],
    "logGenerator": "None"
  },
  {
    "timestamp": "11/12/2022 11:47:59.275179",
    "simulationTimeStamp": "43.00049",
    "logType": "Uav",
    "eventType": "ConditionChanged",
    "logMessages": [
      "Uav Frank condition changed to Hidden"
    ],
    "logGenerator": "None"
  },
  {
    "timestamp": "11/12/2022 11:47:59.275179",
    "simulationTimeStamp": "43.00049",
    "logType": "Uav",
    "eventType": "ConditionChanged",
    "logMessages": [
      "Uav Golf condition changed to Hidden"
    ],
    "logGenerator": "None"
  },
  {
    "timestamp": "11/12/2022 11:47:59.275179",
    "simulationTimeStamp": "43.00049",
    "logType": "Uav",
    "eventType": "ConditionChanged",
    "logMessages": [
      "Uav Hotel condition changed to Hidden"
    ],
    "logGenerator": "None"
  },
  {
    "timestamp": "11/12/2022 11:47:59.275179",
    "simulationTimeStamp": "43.00049",
    "logType": "Uav",
    "eventType": "ConditionChanged",
    "logMessages": [
      "Uav India condition changed to Hidden"
    ],
    "logGenerator": "None"
  },
  {
    "timestamp": "11/12/2022 11:47:59.275179",
    "simulationTimeStamp": "43.00049",
    "logType": "Uav",
    "eventType": "ConditionChanged",
    "logMessages": [
      "Uav John condition changed to Enabled"
    ],
    "logGenerator": "None"
  },
  {
    "timestamp": "11/12/2022 11:47:59.275179",
    "simulationTimeStamp": "43.00049",
    "logType": "Uav",
    "eventType": "ConditionChanged",
    "logMessages": [
      "Uav Kilo condition changed to Hidden"
    ],
    "logGenerator": "None"
  },
  {
    "timestamp": "11/12/2022 11:47:59.276180",
    "simulationTimeStamp": "43.00049",
    "logType": "Uav",
    "eventType": "ConditionChanged",
    "logMessages": [
      "Uav Lima condition changed to Hidden"
    ],
    "logGenerator": "None"
  },
  {
    "timestamp": "11/12/2022 11:47:59.276180",
    "simulationTimeStamp": "43.00049",
    "logType": "Uav",
    "eventType": "ConditionChanged",
    "logMessages": [
      "Uav Mike condition changed to Hidden"
    ],
    "logGenerator": "None"
  },
  {
    "timestamp": "11/12/2022 11:47:59.276180",
    "simulationTimeStamp": "43.00049",
    "logType": "Uav",
    "eventType": "ConditionChanged",
    "logMessages": [
      "Uav Nectar condition changed to Hidden"
    ],
    "logGenerator": "None"
  },
  {
    "timestamp": "11/12/2022 11:47:59.276180",
    "simulationTimeStamp": "43.00049",
    "logType": "Uav",
    "eventType": "ConditionChanged",
    "logMessages": [
      "Uav Oscar condition changed to Hidden"
    ],
    "logGenerator": "None"
  },
  {
    "timestamp": "11/12/2022 11:47:59.276180",
    "simulationTimeStamp": "43.00049",
    "logType": "Uav",
    "eventType": "ConditionChanged",
    "logMessages": [
      "Uav Papa condition changed to Enabled"
    ],
    "logGenerator": "None"
  },
  {
    "timestamp": "11/12/2022 11:47:59.280549",
    "simulationTimeStamp": "43.00049",
    "logType": "Prompts",
    "eventType": "PromptMessageSent",
    "logMessages": [
      "Prompt Message: beginning Mission",
      "Allowed Response Time: 0.0"
    ],
    "logGenerator": "None"
  },
  {
    "timestamp": "11/12/2022 11:48:00.788261",
    "simulationTimeStamp": "44.50613",
    "logType": "Rerouting",
    "eventType": "Rerouting Options Requested",
    "logMessages": [
      " requested rerouting options for uav John",
      "Path start time: 11/12/2022 11:47:59.275179",
      "Rerouting is not needed"
    ],
    "logGenerator": "Host"
  },
  {
    "timestamp": "11/12/2022 11:48:01.527826",
    "simulationTimeStamp": "45.26335",
    "logType": "Rerouting",
    "eventType": "Rerouting Option Previewed",
    "logMessages": [
      "Rerouting option previewed for Uav John ",
      "Path start time: 11/12/2022 11:47:59.275179",
      "Previewed route is good"
    ],
    "logGenerator": "Host"
  },
  {
    "timestamp": "11/12/2022 11:48:01.529198",
    "simulationTimeStamp": "45.26335",
    "logType": "Rerouting",
    "eventType": "Rerouting Option Previewed",
    "logMessages": [
      "Rerouting option previewed for Uav John ",
      "Path start time: 11/12/2022 11:47:59.275179",
      "Previewed route is good"
    ],
    "logGenerator": "Host"
  },
  {
    "timestamp": "11/12/2022 11:48:02.106190",
    "simulationTimeStamp": "45.83889",
    "logType": "Rerouting",
    "eventType": "Rerouting Options Requested",
    "logMessages": [
      " requested rerouting options for uav Papa",
      "Path start time: 11/12/2022 11:47:59.276180",
      "Rerouting is not needed"
    ],
    "logGenerator": "Host"
  },
  {
    "timestamp": "11/12/2022 11:48:03.347343",
    "simulationTimeStamp": "47.08589",
    "logType": "Rerouting",
    "eventType": "Rerouting Option Previewed",
    "logMessages": [
      "Rerouting option previewed for Uav Papa ",
      "Path start time: 11/12/2022 11:47:59.276180",
      "Previewed route is good"
    ],
    "logGenerator": "Host"
  },
  {
    "timestamp": "11/12/2022 11:48:04.526790",
    "simulationTimeStamp": "48.26081",
    "logType": "Rerouting",
    "eventType": "Rerouting Event",
    "logMessages": [
      "Uav Papa  rerouted",
      "Rerouting was not needed",
      "Path start time: 11/12/2022 11:47:59.276180",
      "New route is good"
    ],
    "logGenerator": "Host"
  },
  {
    "timestamp": "11/12/2022 11:48:04.526790",
    "simulationTimeStamp": "48.26081",
    "logType": "Uav",
    "eventType": "ConditionChanged",
    "logMessages": [
      "Uav Papa condition changed to Enabled"
    ],
    "logGenerator": "None"
  },
  {
    "timestamp": "11/12/2022 11:48:04.526790",
    "simulationTimeStamp": "48.26081",
    "logType": "Rerouting",
    "eventType": "Rerouting Option Previewed",
    "logMessages": [
      "Rerouting option previewed for Uav Papa ",
      "Path start time: 11/12/2022 11:47:59.276180",
      "Previewed route is good"
    ],
    "logGenerator": "Host"
  },
  {
    "timestamp": "11/12/2022 11:48:04.526790",
    "simulationTimeStamp": "48.26081",
    "logType": "Rerouting",
    "eventType": "Rerouting Option Previewed",
    "logMessages": [
      "Rerouting option previewed for Uav Papa ",
      "Path start time: 11/12/2022 11:47:59.276180",
      "Previewed route is good"
    ],
    "logGenerator": "Host"
  },
  {
    "timestamp": "11/12/2022 11:48:04.596834",
    "simulationTimeStamp": "48.33583",
    "logType": "Rerouting",
    "eventType": "Rerouting Option Previewed",
    "logMessages": [
      "Rerouting option previewed for Uav Papa ",
      "Path start time: 11/12/2022 11:47:59.276180",
      "Previewed route is good"
    ],
    "logGenerator": "Client"
  }
]