[
  {
    "timestamp": "03/27/2024 01:38:54.961821",
    "simulationTimeStamp": "183.1665",
    "logType": "Uav",
    "eventType": "Created",
    "logMessages": [
      "Uav Alfa created"
    ],
    "logGenerator": "None"
  },
  {
    "timestamp": "03/27/2024 01:38:54.969336",
    "simulationTimeStamp": "183.1665",
    "logType": "Uav",
    "eventType": "Created",
    "logMessages": [
      "Uav Bravo created"
    ],
    "logGenerator": "None"
  },
  {
    "timestamp": "03/27/2024 01:38:54.972337",
    "simulationTimeStamp": "183.1665",
    "logType": "Uav",
    "eventType": "Created",
    "logMessages": [
      "Uav Charlie created"
    ],
    "logGenerator": "None"
  },
  {
    "timestamp": "03/27/2024 01:38:54.976857",
    "simulationTimeStamp": "183.1665",
    "logType": "Uav",
    "eventType": "Created",
    "logMessages": [
      "Uav Delta created"
    ],
    "logGenerator": "None"
  },
  {
    "timestamp": "03/27/2024 01:38:54.980856",
    "simulationTimeStamp": "183.1665",
    "logType": "Uav",
    "eventType": "Created",
    "logMessages": [
      "Uav Echo created"
    ],
    "logGenerator": "None"
  },
  {
    "timestamp": "03/27/2024 01:38:54.983858",
    "simulationTimeStamp": "183.1665",
    "logType": "Uav",
    "eventType": "Created",
    "logMessages": [
      "Uav Frank created"
    ],
    "logGenerator": "None"
  },
  {
    "timestamp": "03/27/2024 01:38:54.987371",
    "simulationTimeStamp": "183.1665",
    "logType": "Uav",
    "eventType": "Created",
    "logMessages": [
      "Uav Golf created"
    ],
    "logGenerator": "None"
  },
  {
    "timestamp": "03/27/2024 01:38:54.990376",
    "simulationTimeStamp": "183.1665",
    "logType": "Uav",
    "eventType": "Created",
    "logMessages": [
      "Uav Hotel created"
    ],
    "logGenerator": "None"
  },
  {
    "timestamp": "03/27/2024 01:38:54.992376",
    "simulationTimeStamp": "183.1665",
    "logType": "Uav",
    "eventType": "Created",
    "logMessages": [
      "Uav India created"
    ],
    "logGenerator": "None"
  },
  {
    "timestamp": "03/27/2024 01:38:54.995377",
    "simulationTimeStamp": "183.1665",
    "logType": "Uav",
    "eventType": "Created",
    "logMessages": [
      "Uav John created"
    ],
    "logGenerator": "None"
  },
  {
    "timestamp": "03/27/2024 01:38:54.997887",
    "simulationTimeStamp": "183.1665",
    "logType": "Uav",
    "eventType": "Created",
    "logMessages": [
      "Uav Kilo created"
    ],
    "logGenerator": "None"
  },
  {
    "timestamp": "03/27/2024 01:38:54.999892",
    "simulationTimeStamp": "183.1665",
    "logType": "Uav",
    "eventType": "Created",
    "logMessages": [
      "Uav Lima created"
    ],
    "logGenerator": "None"
  },
  {
    "timestamp": "03/27/2024 01:38:55.002896",
    "simulationTimeStamp": "183.1665",
    "logType": "Uav",
    "eventType": "Created",
    "logMessages": [
      "Uav Mike created"
    ],
    "logGenerator": "None"
  },
  {
    "timestamp": "03/27/2024 01:38:55.009417",
    "simulationTimeStamp": "183.1665",
    "logType": "Uav",
    "eventType": "Created",
    "logMessages": [
      "Uav Nectar created"
    ],
    "logGenerator": "None"
  },
  {
    "timestamp": "03/27/2024 01:38:55.011935",
    "simulationTimeStamp": "183.1665",
    "logType": "Uav",
    "eventType": "Created",
    "logMessages": [
      "Uav Oscar created"
    ],
    "logGenerator": "None"
  },
  {
    "timestamp": "03/27/2024 01:38:55.014935",
    "simulationTimeStamp": "183.1665",
    "logType": "Uav",
    "eventType": "Created",
    "logMessages": [
      "Uav Papa created"
    ],
    "logGenerator": "None"
  },
  {
    "timestamp": "03/27/2024 01:38:59.946838",
    "simulationTimeStamp": "188.0828",
    "logType": "Uav",
    "eventType": "ConditionChanged",
    "logMessages": [
      "Uav Alfa condition changed to Hidden"
    ],
    "logGenerator": "None"
  },
  {
    "timestamp": "03/27/2024 01:38:59.954492",
    "simulationTimeStamp": "188.0828",
    "logType": "Uav",
    "eventType": "ConditionChanged",
    "logMessages": [
      "Uav Bravo condition changed to Hidden"
    ],
    "logGenerator": "None"
  },
  {
    "timestamp": "03/27/2024 01:38:59.954492",
    "simulationTimeStamp": "188.0828",
    "logType": "Uav",
    "eventType": "ConditionChanged",
    "logMessages": [
      "Uav Charlie condition changed to Hidden"
    ],
    "logGenerator": "None"
  },
  {
    "timestamp": "03/27/2024 01:38:59.954492",
    "simulationTimeStamp": "188.0828",
    "logType": "Uav",
    "eventType": "ConditionChanged",
    "logMessages": [
      "Uav Delta condition changed to Hidden"
    ],
    "logGenerator": "None"
  },
  {
    "timestamp": "03/27/2024 01:38:59.955503",
    "simulationTimeStamp": "188.0828",
    "logType": "Uav",
    "eventType": "ConditionChanged",
    "logMessages": [
      "Uav Echo condition changed to Enabled"
    ],
    "logGenerator": "None"
  },
  {
    "timestamp": "03/27/2024 01:38:59.955503",
    "simulationTimeStamp": "188.0828",
    "logType": "Uav",
    "eventType": "ConditionChanged",
    "logMessages": [
      "Uav Frank condition changed to Hidden"
    ],
    "logGenerator": "None"
  },
  {
    "timestamp": "03/27/2024 01:38:59.955503",
    "simulationTimeStamp": "188.0828",
    "logType": "Uav",
    "eventType": "ConditionChanged",
    "logMessages": [
      "Uav Golf condition changed to Hidden"
    ],
    "logGenerator": "None"
  },
  {
    "timestamp": "03/27/2024 01:38:59.955503",
    "simulationTimeStamp": "188.0828",
    "logType": "Uav",
    "eventType": "ConditionChanged",
    "logMessages": [
      "Uav Hotel condition changed to Hidden"
    ],
    "logGenerator": "None"
  },
  {
    "timestamp": "03/27/2024 01:38:59.956504",
    "simulationTimeStamp": "188.0828",
    "logType": "Uav",
    "eventType": "ConditionChanged",
    "logMessages": [
      "Uav India condition changed to Hidden"
    ],
    "logGenerator": "None"
  },
  {
    "timestamp": "03/27/2024 01:38:59.956504",
    "simulationTimeStamp": "188.0828",
    "logType": "Uav",
    "eventType": "ConditionChanged",
    "logMessages": [
      "Uav John condition changed to Enabled"
    ],
    "logGenerator": "None"
  },
  {
    "timestamp": "03/27/2024 01:38:59.956504",
    "simulationTimeStamp": "188.0828",
    "logType": "Uav",
    "eventType": "ConditionChanged",
    "logMessages": [
      "Uav Kilo condition changed to Hidden"
    ],
    "logGenerator": "None"
  },
  {
    "timestamp": "03/27/2024 01:38:59.956504",
    "simulationTimeStamp": "188.0828",
    "logType": "Uav",
    "eventType": "ConditionChanged",
    "logMessages": [
      "Uav Lima condition changed to Hidden"
    ],
    "logGenerator": "None"
  },
  {
    "timestamp": "03/27/2024 01:38:59.956504",
    "simulationTimeStamp": "188.0828",
    "logType": "Uav",
    "eventType": "ConditionChanged",
    "logMessages": [
      "Uav Mike condition changed to Hidden"
    ],
    "logGenerator": "None"
  },
  {
    "timestamp": "03/27/2024 01:38:59.956504",
    "simulationTimeStamp": "188.0828",
    "logType": "Uav",
    "eventType": "ConditionChanged",
    "logMessages": [
      "Uav Nectar condition changed to Hidden"
    ],
    "logGenerator": "None"
  },
  {
    "timestamp": "03/27/2024 01:38:59.956504",
    "simulationTimeStamp": "188.0828",
    "logType": "Uav",
    "eventType": "ConditionChanged",
    "logMessages": [
      "Uav Oscar condition changed to Hidden"
    ],
    "logGenerator": "None"
  },
  {
    "timestamp": "03/27/2024 01:38:59.956504",
    "simulationTimeStamp": "188.0828",
    "logType": "Uav",
    "eventType": "ConditionChanged",
    "logMessages": [
      "Uav Papa condition changed to Enabled"
    ],
    "logGenerator": "None"
  },
  {
    "timestamp": "03/27/2024 01:38:59.962415",
    "simulationTimeStamp": "188.0828",
    "logType": "Prompts",
    "eventType": "PromptMessageSent",
    "logMessages": [
      "Prompt Message: beginning Mission",
      "Allowed Response Time: 0.0"
    ],
    "logGenerator": "None"
  },
  {
    "timestamp": "03/27/2024 01:39:03.365294",
    "simulationTimeStamp": "191.5066",
    "logType": "Rerouting",
    "eventType": "Rerouting Options Requested",
    "logMessages": [
      " requested rerouting options for uav Papa",
      "Path start time: 03/27/2024 01:38:59.956504",
      "Rerouting is not needed"
    ],
    "logGenerator": "Host"
  },
  {
    "timestamp": "03/27/2024 01:39:04.413300",
    "simulationTimeStamp": "192.5567",
    "logType": "Rerouting",
    "eventType": "Rerouting Option Previewed",
    "logMessages": [
      "Rerouting option previewed for Uav Papa ",
      "Path start time: 03/27/2024 01:38:59.956504",
      "Previewed route is good"
    ],
    "logGenerator": "Host"
  },
  {
    "timestamp": "03/27/2024 01:39:05.415358",
    "simulationTimeStamp": "193.5576",
    "logType": "Rerouting",
    "eventType": "Rerouting Event",
    "logMessages": [
      "Uav Papa  rerouted",
      "Rerouting was not needed",
      "Path start time: 03/27/2024 01:38:59.956504",
      "New route is good"
    ],
    "logGenerator": "Host"
  },
  {
    "timestamp": "03/27/2024 01:39:05.415358",
    "simulationTimeStamp": "193.5576",
    "logType": "Uav",
    "eventType": "ConditionChanged",
    "logMessages": [
      "Uav Papa condition changed to Enabled"
    ],
    "logGenerator": "None"
  },
  {
    "timestamp": "03/27/2024 01:39:05.419711",
    "simulationTimeStamp": "193.5576",
    "logType": "Rerouting",
    "eventType": "Rerouting Option Previewed",
    "logMessages": [
      "Rerouting option previewed for Uav Papa ",
      "Path start time: 03/27/2024 01:38:59.956504",
      "Previewed route is good"
    ],
    "logGenerator": "Host"
  },
  {
    "timestamp": "03/27/2024 01:39:05.419711",
    "simulationTimeStamp": "193.5576",
    "logType": "Rerouting",
    "eventType": "Rerouting Option Previewed",
    "logMessages": [
      "Rerouting option previewed for Uav Papa ",
      "Path start time: 03/27/2024 01:38:59.956504",
      "Previewed route is good"
    ],
    "logGenerator": "Host"
  },
  {
    "timestamp": "03/27/2024 01:39:05.419711",
    "simulationTimeStamp": "193.5576",
    "logType": "Rerouting",
    "eventType": "Rerouting Option Previewed",
    "logMessages": [
      "Rerouting option previewed for Uav Papa ",
      "Path start time: 03/27/2024 01:38:59.956504",
      "Previewed route is good"
    ],
    "logGenerator": "Host"
  },
  {
    "timestamp": "03/27/2024 01:39:05.472442",
    "simulationTimeStamp": "193.6165",
    "logType": "Rerouting",
    "eventType": "Rerouting Option Previewed",
    "logMessages": [
      "Rerouting option previewed for Uav Papa ",
      "Path start time: 03/27/2024 01:38:59.956504",
      "Previewed route is good"
    ],
    "logGenerator": "Client"
  },
  {
    "timestamp": "03/27/2024 01:39:06.709382",
    "simulationTimeStamp": "194.8541",
    "logType": "Rerouting",
    "eventType": "Rerouting Options Requested",
    "logMessages": [
      " requested rerouting options for uav Echo",
      "Path start time: 03/27/2024 01:38:59.954492",
      "Rerouting is not needed"
    ],
    "logGenerator": "Host"
  },
  {
    "timestamp": "03/27/2024 01:39:07.700102",
    "simulationTimeStamp": "195.8442",
    "logType": "Rerouting",
    "eventType": "Rerouting Options Requested",
    "logMessages": [
      " requested rerouting options for uav John",
      "Path start time: 03/27/2024 01:38:59.956504",
      "Rerouting is not needed"
    ],
    "logGenerator": "Host"
  },
  {
    "timestamp": "03/27/2024 01:39:13.720473",
    "simulationTimeStamp": "201.8646",
    "logType": "Rerouting",
    "eventType": "Rerouting Option Previewed",
    "logMessages": [
      "Rerouting option previewed for Uav Echo ",
      "Path start time: 03/27/2024 01:38:59.954492",
      "Previewed route is good"
    ],
    "logGenerator": "Host"
  },
  {
    "timestamp": "03/27/2024 01:39:13.720473",
    "simulationTimeStamp": "201.8646",
    "logType": "Rerouting",
    "eventType": "Rerouting Option Previewed",
    "logMessages": [
      "Rerouting option previewed for Uav Echo ",
      "Path start time: 03/27/2024 01:38:59.954492",
      "Previewed route is good"
    ],
    "logGenerator": "Host"
  },
  {
    "timestamp": "03/27/2024 01:39:13.720473",
    "simulationTimeStamp": "201.8646",
    "logType": "Rerouting",
    "eventType": "Rerouting Option Previewed",
    "logMessages": [
      "Rerouting option previewed for Uav John ",
      "Path start time: 03/27/2024 01:38:59.956504",
      "Previewed route is good"
    ],
    "logGenerator": "Host"
  },
  {
    "timestamp": "03/27/2024 01:39:13.720473",
    "simulationTimeStamp": "201.8646",
    "logType": "Rerouting",
    "eventType": "Rerouting Option Previewed",
    "logMessages": [
      "Rerouting option previewed for Uav John ",
      "Path start time: 03/27/2024 01:38:59.956504",
      "Previewed route is good"
    ],
    "logGenerator": "Host"
  },
  {
    "timestamp": "03/27/2024 01:39:13.929883",
    "simulationTimeStamp": "202.0717",
    "logType": "Uav",
    "eventType": "ConditionChanged",
    "logMessages": [
      "Uav Papa condition changed to Hidden"
    ],
    "logGenerator": "None"
  },
  {
    "timestamp": "03/27/2024 01:39:13.959374",
    "simulationTimeStamp": "202.1021",
    "logType": "Uav",
    "eventType": "ConditionChanged",
    "logMessages": [
      "Uav Alfa condition changed to Enabled"
    ],
    "logGenerator": "None"
  },
  {
    "timestamp": "03/27/2024 01:39:13.959374",
    "simulationTimeStamp": "202.1021",
    "logType": "Uav",
    "eventType": "ConditionChanged",
    "logMessages": [
      "Uav Bravo condition changed to Hidden"
    ],
    "logGenerator": "None"
  },
  {
    "timestamp": "03/27/2024 01:39:13.959374",
    "simulationTimeStamp": "202.1021",
    "logType": "Uav",
    "eventType": "ConditionChanged",
    "logMessages": [
      "Uav Charlie condition changed to Hidden"
    ],
    "logGenerator": "None"
  },
  {
    "timestamp": "03/27/2024 01:39:13.959374",
    "simulationTimeStamp": "202.1021",
    "logType": "Uav",
    "eventType": "ConditionChanged",
    "logMessages": [
      "Uav Delta condition changed to Hidden"
    ],
    "logGenerator": "None"
  },
  {
    "timestamp": "03/27/2024 01:39:13.959374",
    "simulationTimeStamp": "202.1021",
    "logType": "Uav",
    "eventType": "ConditionChanged",
    "logMessages": [
      "Uav Echo condition changed to Hidden"
    ],
    "logGenerator": "None"
  },
  {
    "timestamp": "03/27/2024 01:39:13.960629",
    "simulationTimeStamp": "202.1021",
    "logType": "Uav",
    "eventType": "ConditionChanged",
    "logMessages": [
      "Uav Frank condition changed to Hidden"
    ],
    "logGenerator": "None"
  },
  {
    "timestamp": "03/27/2024 01:39:13.960629",
    "simulationTimeStamp": "202.1021",
    "logType": "Uav",
    "eventType": "ConditionChanged",
    "logMessages": [
      "Uav Golf condition changed to Enabled"
    ],
    "logGenerator": "None"
  },
  {
    "timestamp": "03/27/2024 01:39:13.960629",
    "simulationTimeStamp": "202.1021",
    "logType": "Uav",
    "eventType": "ConditionChanged",
    "logMessages": [
      "Uav Hotel condition changed to Hidden"
    ],
    "logGenerator": "None"
  },
  {
    "timestamp": "03/27/2024 01:39:13.960629",
    "simulationTimeStamp": "202.1021",
    "logType": "Uav",
    "eventType": "ConditionChanged",
    "logMessages": [
      "Uav India condition changed to Enabled"
    ],
    "logGenerator": "None"
  },
  {
    "timestamp": "03/27/2024 01:39:13.960629",
    "simulationTimeStamp": "202.1021",
    "logType": "Uav",
    "eventType": "ConditionChanged",
    "logMessages": [
      "Uav John condition changed to Enabled"
    ],
    "logGenerator": "None"
  },
  {
    "timestamp": "03/27/2024 01:39:13.960629",
    "simulationTimeStamp": "202.1021",
    "logType": "Uav",
    "eventType": "ConditionChanged",
    "logMessages": [
      "Uav Kilo condition changed to Hidden"
    ],
    "logGenerator": "None"
  },
  {
    "timestamp": "03/27/2024 01:39:13.960629",
    "simulationTimeStamp": "202.1021",
    "logType": "Uav",
    "eventType": "ConditionChanged",
    "logMessages": [
      "Uav Lima condition changed to Hidden"
    ],
    "logGenerator": "None"
  },
  {
    "timestamp": "03/27/2024 01:39:13.960629",
    "simulationTimeStamp": "202.1021",
    "logType": "Uav",
    "eventType": "ConditionChanged",
    "logMessages": [
      "Uav Mike condition changed to Hidden"
    ],
    "logGenerator": "None"
  },
  {
    "timestamp": "03/27/2024 01:39:13.962134",
    "simulationTimeStamp": "202.1021",
    "logType": "Uav",
    "eventType": "ConditionChanged",
    "logMessages": [
      "Uav Nectar condition changed to Hidden"
    ],
    "logGenerator": "None"
  },
  {
    "timestamp": "03/27/2024 01:39:13.962134",
    "simulationTimeStamp": "202.1021",
    "logType": "Uav",
    "eventType": "ConditionChanged",
    "logMessages": [
      "Uav Oscar condition changed to Hidden"
    ],
    "logGenerator": "None"
  },
  {
    "timestamp": "03/27/2024 01:39:14.949809",
    "simulationTimeStamp": "203.0825",
    "logType": "Prompts",
    "eventType": "PromptMessageSent",
    "logMessages": [
      "Prompt Message: Which UAV/s had a bad projected route?",
      "Allowed Response Time: 0.0",
      "Correct Response Options:  | #10",
      "Wrong Response Options:  | #0 | #1 | #2 | #3 | #4 | #5 | #6 | #7 | #8 | #9 | #11 | #12 | #13 | #14 | #15"
    ],
    "logGenerator": "None"
  },
  {
    "timestamp": "03/27/2024 01:39:15.726241",
    "simulationTimeStamp": "203.8548",
    "logType": "Rerouting",
    "eventType": "Rerouting Options Requested",
    "logMessages": [
      " requested rerouting options for uav John",
      "Path start time: 03/27/2024 01:39:13.960629",
      "Rerouting is not needed"
    ],
    "logGenerator": "Client"
  },
  {
    "timestamp": "03/27/2024 01:39:16.279580",
    "simulationTimeStamp": "204.4149",
    "logType": "Rerouting",
    "eventType": "Rerouting Options Requested",
    "logMessages": [
      " requested rerouting options for uav Golf",
      "Path start time: 03/27/2024 01:39:13.960629",
      "Rerouting is not needed"
    ],
    "logGenerator": "Client"
  },
  {
    "timestamp": "03/27/2024 01:39:17.028831",
    "simulationTimeStamp": "205.1653",
    "logType": "Rerouting",
    "eventType": "Rerouting Options Requested",
    "logMessages": [
      " requested rerouting options for uav India",
      "Path start time: 03/27/2024 01:39:13.960629",
      "Rerouting is not needed"
    ],
    "logGenerator": "Client"
  },
  {
    "timestamp": "03/27/2024 01:39:17.615177",
    "simulationTimeStamp": "205.7507",
    "logType": "Rerouting",
    "eventType": "Rerouting Options Requested",
    "logMessages": [
      " requested rerouting options for uav Alfa",
      "Path start time: 03/27/2024 01:39:13.958378",
      "Rerouting is not needed"
    ],
    "logGenerator": "Client"
  },
  {
    "timestamp": "03/27/2024 01:39:21.931162",
    "simulationTimeStamp": "210.0715",
    "logType": "Prompts",
    "eventType": "PromptMessageSent",
    "logMessages": [
      "Prompt Message: Detecting UAV 6 flying away from NFZ?",
      "Allowed Response Time: 10.0",
      "Correct Response Options:  | Confirm",
      "Wrong Response Options:  | Deny"
    ],
    "logGenerator": "None"
  },
  {
    "timestamp": "03/27/2024 01:39:27.937627",
    "simulationTimeStamp": "216.0755",
    "logType": "Uav",
    "eventType": "ConditionChanged",
    "logMessages": [
      "Uav Papa condition changed to Hidden"
    ],
    "logGenerator": "None"
  },
  {
    "timestamp": "03/27/2024 01:39:27.972418",
    "simulationTimeStamp": "216.1149",
    "logType": "Uav",
    "eventType": "ConditionChanged",
    "logMessages": [
      "Uav Alfa condition changed to Hidden"
    ],
    "logGenerator": "None"
  },
  {
    "timestamp": "03/27/2024 01:39:27.972418",
    "simulationTimeStamp": "216.1149",
    "logType": "Uav",
    "eventType": "ConditionChanged",
    "logMessages": [
      "Uav Bravo condition changed to Hidden"
    ],
    "logGenerator": "None"
  },
  {
    "timestamp": "03/27/2024 01:39:27.972418",
    "simulationTimeStamp": "216.1149",
    "logType": "Uav",
    "eventType": "ConditionChanged",
    "logMessages": [
      "Uav Charlie condition changed to Hidden"
    ],
    "logGenerator": "None"
  },
  {
    "timestamp": "03/27/2024 01:39:27.972932",
    "simulationTimeStamp": "216.1149",
    "logType": "Uav",
    "eventType": "ConditionChanged",
    "logMessages": [
      "Uav Delta condition changed to Enabled"
    ],
    "logGenerator": "None"
  },
  {
    "timestamp": "03/27/2024 01:39:27.972932",
    "simulationTimeStamp": "216.1149",
    "logType": "Uav",
    "eventType": "ConditionChanged",
    "logMessages": [
      "Uav Echo condition changed to Hidden"
    ],
    "logGenerator": "None"
  },
  {
    "timestamp": "03/27/2024 01:39:27.972932",
    "simulationTimeStamp": "216.1149",
    "logType": "Uav",
    "eventType": "ConditionChanged",
    "logMessages": [
      "Uav Frank condition changed to Enabled"
    ],
    "logGenerator": "None"
  },
  {
    "timestamp": "03/27/2024 01:39:27.972932",
    "simulationTimeStamp": "216.1149",
    "logType": "Uav",
    "eventType": "ConditionChanged",
    "logMessages": [
      "Uav Golf condition changed to Hidden"
    ],
    "logGenerator": "None"
  },
  {
    "timestamp": "03/27/2024 01:39:27.972932",
    "simulationTimeStamp": "216.1149",
    "logType": "Uav",
    "eventType": "ConditionChanged",
    "logMessages": [
      "Uav Hotel condition changed to Enabled"
    ],
    "logGenerator": "None"
  },
  {
    "timestamp": "03/27/2024 01:39:27.974330",
    "simulationTimeStamp": "216.1149",
    "logType": "Uav",
    "eventType": "ConditionChanged",
    "logMessages": [
      "Uav India condition changed to Hidden"
    ],
    "logGenerator": "None"
  },
  {
    "timestamp": "03/27/2024 01:39:27.974330",
    "simulationTimeStamp": "216.1149",
    "logType": "Uav",
    "eventType": "ConditionChanged",
    "logMessages": [
      "Uav John condition changed to Hidden"
    ],
    "logGenerator": "None"
  },
  {
    "timestamp": "03/27/2024 01:39:27.974330",
    "simulationTimeStamp": "216.1149",
    "logType": "Uav",
    "eventType": "ConditionChanged",
    "logMessages": [
      "Uav Kilo condition changed to Hidden"
    ],
    "logGenerator": "None"
  },
  {
    "timestamp": "03/27/2024 01:39:27.974330",
    "simulationTimeStamp": "216.1149",
    "logType": "Uav",
    "eventType": "ConditionChanged",
    "logMessages": [
      "Uav Lima condition changed to Hidden"
    ],
    "logGenerator": "None"
  },
  {
    "timestamp": "03/27/2024 01:39:27.974330",
    "simulationTimeStamp": "216.1149",
    "logType": "Uav",
    "eventType": "ConditionChanged",
    "logMessages": [
      "Uav Mike condition changed to Enabled"
    ],
    "logGenerator": "None"
  },
  {
    "timestamp": "03/27/2024 01:39:27.974330",
    "simulationTimeStamp": "216.1149",
    "logType": "Uav",
    "eventType": "ConditionChanged",
    "logMessages": [
      "Uav Nectar condition changed to Hidden"
    ],
    "logGenerator": "None"
  },
  {
    "timestamp": "03/27/2024 01:39:27.974330",
    "simulationTimeStamp": "216.1149",
    "logType": "Uav",
    "eventType": "ConditionChanged",
    "logMessages": [
      "Uav Oscar condition changed to Hidden"
    ],
    "logGenerator": "None"
  },
  {
    "timestamp": "03/27/2024 01:39:28.005353",
    "simulationTimeStamp": "216.1499",
    "logType": "Rerouting",
    "eventType": "Rerouting Option Previewed",
    "logMessages": [
      "Rerouting option previewed for Uav John ",
      "Path start time: 03/27/2024 01:39:27.974330",
      "Previewed route is good"
    ],
    "logGenerator": "Client"
  },
  {
    "timestamp": "03/27/2024 01:39:28.005353",
    "simulationTimeStamp": "216.1499",
    "logType": "Rerouting",
    "eventType": "Rerouting Option Previewed",
    "logMessages": [
      "Rerouting option previewed for Uav John ",
      "Path start time: 03/27/2024 01:39:27.974330",
      "Previewed route is good"
    ],
    "logGenerator": "Client"
  },
  {
    "timestamp": "03/27/2024 01:39:28.005353",
    "simulationTimeStamp": "216.1499",
    "logType": "Rerouting",
    "eventType": "Rerouting Option Previewed",
    "logMessages": [
      "Rerouting option previewed for Uav Golf ",
      "Path start time: 03/27/2024 01:39:27.972932",
      "Previewed route is good"
    ],
    "logGenerator": "Client"
  },
  {
    "timestamp": "03/27/2024 01:39:28.005353",
    "simulationTimeStamp": "216.1499",
    "logType": "Rerouting",
    "eventType": "Rerouting Option Previewed",
    "logMessages": [
      "Rerouting option previewed for Uav Golf ",
      "Path start time: 03/27/2024 01:39:27.972932",
      "Previewed route is good"
    ],
    "logGenerator": "Client"
  },
  {
    "timestamp": "03/27/2024 01:39:28.005353",
    "simulationTimeStamp": "216.1499",
    "logType": "Rerouting",
    "eventType": "Rerouting Option Previewed",
    "logMessages": [
      "Rerouting option previewed for Uav India ",
      "Path start time: 03/27/2024 01:39:27.972932",
      "Previewed route is good"
    ],
    "logGenerator": "Client"
  },
  {
    "timestamp": "03/27/2024 01:39:28.005353",
    "simulationTimeStamp": "216.1499",
    "logType": "Rerouting",
    "eventType": "Rerouting Option Previewed",
    "logMessages": [
      "Rerouting option previewed for Uav India ",
      "Path start time: 03/27/2024 01:39:27.972932",
      "Previewed route is good"
    ],
    "logGenerator": "Client"
  },
  {
    "timestamp": "03/27/2024 01:39:28.005353",
    "simulationTimeStamp": "216.1499",
    "logType": "Rerouting",
    "eventType": "Rerouting Option Previewed",
    "logMessages": [
      "Rerouting option previewed for Uav Alfa ",
      "Path start time: 03/27/2024 01:39:27.970912",
      "Previewed route is good"
    ],
    "logGenerator": "Client"
  },
  {
    "timestamp": "03/27/2024 01:39:28.005353",
    "simulationTimeStamp": "216.1499",
    "logType": "Rerouting",
    "eventType": "Rerouting Option Previewed",
    "logMessages": [
      "Rerouting option previewed for Uav Alfa ",
      "Path start time: 03/27/2024 01:39:27.970912",
      "Previewed route is good"
    ],
    "logGenerator": "Client"
  },
  {
    "timestamp": "03/27/2024 01:39:33.451637",
    "simulationTimeStamp": "221.5865",
    "logType": "Rerouting",
    "eventType": "Rerouting Options Requested",
    "logMessages": [
      " requested rerouting options for uav Delta",
      "Path start time: 03/27/2024 01:39:27.972932",
      "Rerouting is not needed"
    ],
    "logGenerator": "Client"
  },
  {
    "timestamp": "03/27/2024 01:39:34.458637",
    "simulationTimeStamp": "222.6029",
    "logType": "Rerouting",
    "eventType": "Rerouting Option Previewed",
    "logMessages": [
      "Rerouting option previewed for Uav Delta ",
      "Path start time: 03/27/2024 01:39:27.972932",
      "Previewed route is good"
    ],
    "logGenerator": "Client"
  },
  {
    "timestamp": "03/27/2024 01:39:35.246476",
    "simulationTimeStamp": "223.383",
    "logType": "Rerouting",
    "eventType": "Rerouting Option Previewed",
    "logMessages": [
      "Rerouting option previewed for Uav Delta ",
      "Path start time: 03/27/2024 01:39:27.972932",
      "Previewed route is good"
    ],
    "logGenerator": "Host"
  },
  {
    "timestamp": "03/27/2024 01:39:35.246476",
    "simulationTimeStamp": "223.383",
    "logType": "Rerouting",
    "eventType": "Rerouting Option Previewed",
    "logMessages": [
      "Rerouting option previewed for Uav Delta ",
      "Path start time: 03/27/2024 01:39:27.972932",
      "Previewed route is good"
    ],
    "logGenerator": "Client"
  },
  {
    "timestamp": "03/27/2024 01:39:36.203378",
    "simulationTimeStamp": "224.3405",
    "logType": "Rerouting",
    "eventType": "Rerouting Options Requested",
    "logMessages": [
      " requested rerouting options for uav Mike",
      "Path start time: 03/27/2024 01:39:27.974330",
      "Rerouting is not needed"
    ],
    "logGenerator": "Client"
  },
  {
    "timestamp": "03/27/2024 01:39:41.935729",
    "simulationTimeStamp": "230.0795",
    "logType": "Uav",
    "eventType": "ConditionChanged",
    "logMessages": [
      "Uav Papa condition changed to Hidden"
    ],
    "logGenerator": "None"
  },
  {
    "timestamp": "03/27/2024 01:39:41.997744",
    "simulationTimeStamp": "230.1421",
    "logType": "Rerouting",
    "eventType": "Rerouting Option Previewed",
    "logMessages": [
      "Rerouting option previewed for Uav Mike ",
      "Path start time: 03/27/2024 01:39:27.974330",
      "Previewed route is good"
    ],
    "logGenerator": "Client"
  },
  {
    "timestamp": "03/27/2024 01:39:41.997744",
    "simulationTimeStamp": "230.1421",
    "logType": "Rerouting",
    "eventType": "Rerouting Option Previewed",
    "logMessages": [
      "Rerouting option previewed for Uav Mike ",
      "Path start time: 03/27/2024 01:39:27.974330",
      "Previewed route is good"
    ],
    "logGenerator": "Client"
  },
  {
    "timestamp": "03/27/2024 01:39:41.999867",
    "simulationTimeStamp": "230.1421",
    "logType": "Uav",
    "eventType": "ConditionChanged",
    "logMessages": [
      "Uav Alfa condition changed to Enabled"
    ],
    "logGenerator": "None"
  },
  {
    "timestamp": "03/27/2024 01:39:41.999867",
    "simulationTimeStamp": "230.1421",
    "logType": "Uav",
    "eventType": "ConditionChanged",
    "logMessages": [
      "Uav Bravo condition changed to Hidden"
    ],
    "logGenerator": "None"
  },
  {
    "timestamp": "03/27/2024 01:39:41.999867",
    "simulationTimeStamp": "230.1421",
    "logType": "Uav",
    "eventType": "ConditionChanged",
    "logMessages": [
      "Uav Charlie condition changed to Hidden"
    ],
    "logGenerator": "None"
  },
  {
    "timestamp": "03/27/2024 01:39:41.999867",
    "simulationTimeStamp": "230.1421",
    "logType": "Uav",
    "eventType": "ConditionChanged",
    "logMessages": [
      "Uav Delta condition changed to Hidden"
    ],
    "logGenerator": "None"
  },
  {
    "timestamp": "03/27/2024 01:39:41.999867",
    "simulationTimeStamp": "230.1421",
    "logType": "Uav",
    "eventType": "ConditionChanged",
    "logMessages": [
      "Uav Echo condition changed to Hidden"
    ],
    "logGenerator": "None"
  },
  {
    "timestamp": "03/27/2024 01:39:41.999867",
    "simulationTimeStamp": "230.1421",
    "logType": "Uav",
    "eventType": "ConditionChanged",
    "logMessages": [
      "Uav Frank condition changed to Hidden"
    ],
    "logGenerator": "None"
  },
  {
    "timestamp": "03/27/2024 01:39:41.999867",
    "simulationTimeStamp": "230.1421",
    "logType": "Uav",
    "eventType": "ConditionChanged",
    "logMessages": [
      "Uav Golf condition changed to Enabled"
    ],
    "logGenerator": "None"
  },
  {
    "timestamp": "03/27/2024 01:39:42.000867",
    "simulationTimeStamp": "230.1421",
    "logType": "Uav",
    "eventType": "ConditionChanged",
    "logMessages": [
      "Uav Hotel condition changed to Hidden"
    ],
    "logGenerator": "None"
  },
  {
    "timestamp": "03/27/2024 01:39:42.000867",
    "simulationTimeStamp": "230.1421",
    "logType": "Uav",
    "eventType": "ConditionChanged",
    "logMessages": [
      "Uav India condition changed to Hidden"
    ],
    "logGenerator": "None"
  },
  {
    "timestamp": "03/27/2024 01:39:42.000867",
    "simulationTimeStamp": "230.1421",
    "logType": "Uav",
    "eventType": "ConditionChanged",
    "logMessages": [
      "Uav John condition changed to Enabled"
    ],
    "logGenerator": "None"
  },
  {
    "timestamp": "03/27/2024 01:39:42.000867",
    "simulationTimeStamp": "230.1421",
    "logType": "Uav",
    "eventType": "ConditionChanged",
    "logMessages": [
      "Uav Kilo condition changed to Hidden"
    ],
    "logGenerator": "None"
  },
  {
    "timestamp": "03/27/2024 01:39:42.000867",
    "simulationTimeStamp": "230.1421",
    "logType": "Uav",
    "eventType": "ConditionChanged",
    "logMessages": [
      "Uav Lima condition changed to Enabled"
    ],
    "logGenerator": "None"
  },
  {
    "timestamp": "03/27/2024 01:39:42.000867",
    "simulationTimeStamp": "230.1421",
    "logType": "Uav",
    "eventType": "ConditionChanged",
    "logMessages": [
      "Uav Mike condition changed to Hidden"
    ],
    "logGenerator": "None"
  },
  {
    "timestamp": "03/27/2024 01:39:42.000867",
    "simulationTimeStamp": "230.1421",
    "logType": "Uav",
    "eventType": "ConditionChanged",
    "logMessages": [
      "Uav Nectar condition changed to Hidden"
    ],
    "logGenerator": "None"
  },
  {
    "timestamp": "03/27/2024 01:39:42.001866",
    "simulationTimeStamp": "230.1421",
    "logType": "Uav",
    "eventType": "ConditionChanged",
    "logMessages": [
      "Uav Oscar condition changed to Hidden"
    ],
    "logGenerator": "None"
  },
  {
    "timestamp": "03/27/2024 01:39:43.939441",
    "simulationTimeStamp": "232.0816",
    "logType": "Fuel",
    "eventType": "Fuel Condition Changed",
    "logMessages": [
      "UAV Nectar fuel leak event started"
    ],
    "logGenerator": "None"
  },
  {
    "timestamp": "03/27/2024 01:39:45.484440",
    "simulationTimeStamp": "233.6203",
    "logType": "Rerouting",
    "eventType": "Rerouting Options Requested",
    "logMessages": [
      " requested rerouting options for uav John",
      "Path start time: 03/27/2024 01:39:42.000867",
      "Rerouting is not needed"
    ],
    "logGenerator": "Client"
  },
  {
    "timestamp": "03/27/2024 01:39:46.932657",
    "simulationTimeStamp": "235.0676",
    "logType": "Rerouting",
    "eventType": "Rerouting Options Requested",
    "logMessages": [
      " requested rerouting options for uav Alfa",
      "Path start time: 03/27/2024 01:39:41.998867",
      "Rerouting is not needed"
    ],
    "logGenerator": "Client"
  },
  {
    "timestamp": "03/27/2024 01:39:53.942612",
    "simulationTimeStamp": "242.086",
    "logType": "Fuel",
    "eventType": "Fuel Condition Changed",
    "logMessages": [
      "UAV Nectar fuel leak became fatal "
    ],
    "logGenerator": "None"
  },
  {
    "timestamp": "03/27/2024 01:39:55.956017",
    "simulationTimeStamp": "244.0969",
    "logType": "Uav",
    "eventType": "ConditionChanged",
    "logMessages": [
      "Uav Papa condition changed to Enabled"
    ],
    "logGenerator": "None"
  },
  {
    "timestamp": "03/27/2024 01:39:56.028715",
    "simulationTimeStamp": "244.1725",
    "logType": "Rerouting",
    "eventType": "Rerouting Option Previewed",
    "logMessages": [
      "Rerouting option previewed for Uav John ",
      "Path start time: 03/27/2024 01:39:42.000867",
      "Previewed route is good"
    ],
    "logGenerator": "Client"
  },
  {
    "timestamp": "03/27/2024 01:39:56.028715",
    "simulationTimeStamp": "244.1725",
    "logType": "Rerouting",
    "eventType": "Rerouting Option Previewed",
    "logMessages": [
      "Rerouting option previewed for Uav John ",
      "Path start time: 03/27/2024 01:39:42.000867",
      "Previewed route is good"
    ],
    "logGenerator": "Client"
  },
  {
    "timestamp": "03/27/2024 01:39:56.028715",
    "simulationTimeStamp": "244.1725",
    "logType": "Rerouting",
    "eventType": "Rerouting Option Previewed",
    "logMessages": [
      "Rerouting option previewed for Uav Alfa ",
      "Path start time: 03/27/2024 01:39:41.998867",
      "Previewed route is good"
    ],
    "logGenerator": "Client"
  },
  {
    "timestamp": "03/27/2024 01:39:56.028715",
    "simulationTimeStamp": "244.1725",
    "logType": "Rerouting",
    "eventType": "Rerouting Option Previewed",
    "logMessages": [
      "Rerouting option previewed for Uav Alfa ",
      "Path start time: 03/27/2024 01:39:41.998867",
      "Previewed route is good"
    ],
    "logGenerator": "Client"
  },
  {
    "timestamp": "03/27/2024 01:39:56.028715",
    "simulationTimeStamp": "244.1725",
    "logType": "Uav",
    "eventType": "ConditionChanged",
    "logMessages": [
      "Uav Alfa condition changed to Hidden"
    ],
    "logGenerator": "None"
  },
  {
    "timestamp": "03/27/2024 01:39:56.028715",
    "simulationTimeStamp": "244.1725",
    "logType": "Uav",
    "eventType": "ConditionChanged",
    "logMessages": [
      "Uav Bravo condition changed to Hidden"
    ],
    "logGenerator": "None"
  },
  {
    "timestamp": "03/27/2024 01:39:56.030133",
    "simulationTimeStamp": "244.1725",
    "logType": "Uav",
    "eventType": "ConditionChanged",
    "logMessages": [
      "Uav Charlie condition changed to Enabled"
    ],
    "logGenerator": "None"
  },
  {
    "timestamp": "03/27/2024 01:39:56.030133",
    "simulationTimeStamp": "244.1725",
    "logType": "Uav",
    "eventType": "ConditionChanged",
    "logMessages": [
      "Uav Delta condition changed to Hidden"
    ],
    "logGenerator": "None"
  },
  {
    "timestamp": "03/27/2024 01:39:56.030133",
    "simulationTimeStamp": "244.1725",
    "logType": "Uav",
    "eventType": "ConditionChanged",
    "logMessages": [
      "Uav Echo condition changed to Hidden"
    ],
    "logGenerator": "None"
  },
  {
    "timestamp": "03/27/2024 01:39:56.030133",
    "simulationTimeStamp": "244.1725",
    "logType": "Uav",
    "eventType": "ConditionChanged",
    "logMessages": [
      "Uav Frank condition changed to Hidden"
    ],
    "logGenerator": "None"
  },
  {
    "timestamp": "03/27/2024 01:39:56.030133",
    "simulationTimeStamp": "244.1725",
    "logType": "Uav",
    "eventType": "ConditionChanged",
    "logMessages": [
      "Uav Golf condition changed to Hidden"
    ],
    "logGenerator": "None"
  },
  {
    "timestamp": "03/27/2024 01:39:56.031208",
    "simulationTimeStamp": "244.1725",
    "logType": "Uav",
    "eventType": "ConditionChanged",
    "logMessages": [
      "Uav Hotel condition changed to Enabled"
    ],
    "logGenerator": "None"
  },
  {
    "timestamp": "03/27/2024 01:39:56.031208",
    "simulationTimeStamp": "244.1725",
    "logType": "Uav",
    "eventType": "ConditionChanged",
    "logMessages": [
      "Uav India condition changed to Enabled"
    ],
    "logGenerator": "None"
  },
  {
    "timestamp": "03/27/2024 01:39:56.031208",
    "simulationTimeStamp": "244.1725",
    "logType": "Uav",
    "eventType": "ConditionChanged",
    "logMessages": [
      "Uav John condition changed to Hidden"
    ],
    "logGenerator": "None"
  },
  {
    "timestamp": "03/27/2024 01:39:56.031208",
    "simulationTimeStamp": "244.1725",
    "logType": "Uav",
    "eventType": "ConditionChanged",
    "logMessages": [
      "Uav Kilo condition changed to Enabled"
    ],
    "logGenerator": "None"
  },
  {
    "timestamp": "03/27/2024 01:39:56.031208",
    "simulationTimeStamp": "244.1725",
    "logType": "Uav",
    "eventType": "ConditionChanged",
    "logMessages": [
      "Uav Lima condition changed to Hidden"
    ],
    "logGenerator": "None"
  },
  {
    "timestamp": "03/27/2024 01:39:56.031208",
    "simulationTimeStamp": "244.1725",
    "logType": "Uav",
    "eventType": "ConditionChanged",
    "logMessages": [
      "Uav Mike condition changed to Hidden"
    ],
    "logGenerator": "None"
  },
  {
    "timestamp": "03/27/2024 01:39:56.031208",
    "simulationTimeStamp": "244.1725",
    "logType": "Uav",
    "eventType": "ConditionChanged",
    "logMessages": [
      "Uav Nectar condition changed to Hidden"
    ],
    "logGenerator": "None"
  },
  {
    "timestamp": "03/27/2024 01:39:56.031208",
    "simulationTimeStamp": "244.1725",
    "logType": "Uav",
    "eventType": "ConditionChanged",
    "logMessages": [
      "Uav Oscar condition changed to Hidden"
    ],
    "logGenerator": "None"
  },
  {
    "timestamp": "03/27/2024 01:40:04.351351",
    "simulationTimeStamp": "252.486",
    "logType": "Rerouting",
    "eventType": "Rerouting Options Requested",
    "logMessages": [
      " requested rerouting options for uav Charlie",
      "Path start time: 03/27/2024 01:39:56.030133",
      "Rerouting is not needed"
    ],
    "logGenerator": "Client"
  },
  {
    "timestamp": "03/27/2024 01:40:05.253861",
    "simulationTimeStamp": "253.3894",
    "logType": "Rerouting",
    "eventType": "Rerouting Options Requested",
    "logMessages": [
      " requested rerouting options for uav India",
      "Path start time: 03/27/2024 01:39:56.031208",
      "Rerouting is not needed"
    ],
    "logGenerator": "Client"
  },
  {
    "timestamp": "03/27/2024 01:40:05.849877",
    "simulationTimeStamp": "253.9842",
    "logType": "Rerouting",
    "eventType": "Rerouting Options Requested",
    "logMessages": [
      " requested rerouting options for uav Kilo",
      "Path start time: 03/27/2024 01:39:56.031208",
      "Rerouting is not needed"
    ],
    "logGenerator": "Client"
  },
  {
    "timestamp": "03/27/2024 01:40:08.046247",
    "simulationTimeStamp": "256.1901",
    "logType": "Rerouting",
    "eventType": "Rerouting Option Previewed",
    "logMessages": [
      "Rerouting option previewed for Uav Kilo ",
      "Path start time: 03/27/2024 01:39:56.031208",
      "Previewed route is good"
    ],
    "logGenerator": "Client"
  },
  {
    "timestamp": "03/27/2024 01:40:08.657991",
    "simulationTimeStamp": "256.8013",
    "logType": "Rerouting",
    "eventType": "Rerouting Option Previewed",
    "logMessages": [
      "Rerouting option previewed for Uav Kilo ",
      "Path start time: 03/27/2024 01:39:56.031208",
      "Previewed route is good"
    ],
    "logGenerator": "Host"
  },
  {
    "timestamp": "03/27/2024 01:40:08.657991",
    "simulationTimeStamp": "256.8013",
    "logType": "Rerouting",
    "eventType": "Rerouting Option Previewed",
    "logMessages": [
      "Rerouting option previewed for Uav Kilo ",
      "Path start time: 03/27/2024 01:39:56.031208",
      "Previewed route is good"
    ],
    "logGenerator": "Client"
  },
  {
    "timestamp": "03/27/2024 01:40:09.978876",
    "simulationTimeStamp": "258.1211",
    "logType": "Uav",
    "eventType": "ConditionChanged",
    "logMessages": [
      "Uav Papa condition changed to Hidden"
    ],
    "logGenerator": "None"
  },
  {
    "timestamp": "03/27/2024 01:40:10.038131",
    "simulationTimeStamp": "258.1808",
    "logType": "Uav",
    "eventType": "ConditionChanged",
    "logMessages": [
      "Uav Alfa condition changed to Enabled"
    ],
    "logGenerator": "None"
  },
  {
    "timestamp": "03/27/2024 01:40:10.039657",
    "simulationTimeStamp": "258.1808",
    "logType": "Uav",
    "eventType": "ConditionChanged",
    "logMessages": [
      "Uav Bravo condition changed to Hidden"
    ],
    "logGenerator": "None"
  },
  {
    "timestamp": "03/27/2024 01:40:10.039657",
    "simulationTimeStamp": "258.1808",
    "logType": "Uav",
    "eventType": "ConditionChanged",
    "logMessages": [
      "Uav Charlie condition changed to Hidden"
    ],
    "logGenerator": "None"
  },
  {
    "timestamp": "03/27/2024 01:40:10.039657",
    "simulationTimeStamp": "258.1808",
    "logType": "Uav",
    "eventType": "ConditionChanged",
    "logMessages": [
      "Uav Delta condition changed to Hidden"
    ],
    "logGenerator": "None"
  },
  {
    "timestamp": "03/27/2024 01:40:10.039657",
    "simulationTimeStamp": "258.1808",
    "logType": "Uav",
    "eventType": "ConditionChanged",
    "logMessages": [
      "Uav Echo condition changed to Enabled"
    ],
    "logGenerator": "None"
  },
  {
    "timestamp": "03/27/2024 01:40:10.039657",
    "simulationTimeStamp": "258.1808",
    "logType": "Uav",
    "eventType": "ConditionChanged",
    "logMessages": [
      "Uav Frank condition changed to Hidden"
    ],
    "logGenerator": "None"
  },
  {
    "timestamp": "03/27/2024 01:40:10.039657",
    "simulationTimeStamp": "258.1808",
    "logType": "Uav",
    "eventType": "ConditionChanged",
    "logMessages": [
      "Uav Golf condition changed to Hidden"
    ],
    "logGenerator": "None"
  },
  {
    "timestamp": "03/27/2024 01:40:10.040664",
    "simulationTimeStamp": "258.1808",
    "logType": "Uav",
    "eventType": "ConditionChanged",
    "logMessages": [
      "Uav Hotel condition changed to Hidden"
    ],
    "logGenerator": "None"
  },
  {
    "timestamp": "03/27/2024 01:40:10.040664",
    "simulationTimeStamp": "258.1808",
    "logType": "Uav",
    "eventType": "ConditionChanged",
    "logMessages": [
      "Uav India condition changed to Hidden"
    ],
    "logGenerator": "None"
  },
  {
    "timestamp": "03/27/2024 01:40:10.040664",
    "simulationTimeStamp": "258.1808",
    "logType": "Uav",
    "eventType": "ConditionChanged",
    "logMessages": [
      "Uav John condition changed to Enabled"
    ],
    "logGenerator": "None"
  },
  {
    "timestamp": "03/27/2024 01:40:10.040664",
    "simulationTimeStamp": "258.1808",
    "logType": "Uav",
    "eventType": "ConditionChanged",
    "logMessages": [
      "Uav Kilo condition changed to Hidden"
    ],
    "logGenerator": "None"
  },
  {
    "timestamp": "03/27/2024 01:40:10.040664",
    "simulationTimeStamp": "258.1808",
    "logType": "Uav",
    "eventType": "ConditionChanged",
    "logMessages": [
      "Uav Lima condition changed to Hidden"
    ],
    "logGenerator": "None"
  },
  {
    "timestamp": "03/27/2024 01:40:10.041664",
    "simulationTimeStamp": "258.1808",
    "logType": "Uav",
    "eventType": "ConditionChanged",
    "logMessages": [
      "Uav Mike condition changed to Hidden"
    ],
    "logGenerator": "None"
  },
  {
    "timestamp": "03/27/2024 01:40:10.041664",
    "simulationTimeStamp": "258.1808",
    "logType": "Uav",
    "eventType": "ConditionChanged",
    "logMessages": [
      "Uav Nectar condition changed to Enabled"
    ],
    "logGenerator": "None"
  },
  {
    "timestamp": "03/27/2024 01:40:10.041664",
    "simulationTimeStamp": "258.1808",
    "logType": "Uav",
    "eventType": "ConditionChanged",
    "logMessages": [
      "Uav Oscar condition changed to Hidden"
    ],
    "logGenerator": "None"
  },
  {
    "timestamp": "03/27/2024 01:40:10.073403",
    "simulationTimeStamp": "258.2175",
    "logType": "Rerouting",
    "eventType": "Rerouting Option Previewed",
    "logMessages": [
      "Rerouting option previewed for Uav Charlie ",
      "Path start time: 03/27/2024 01:40:10.039657",
      "Previewed route is good"
    ],
    "logGenerator": "Client"
  },
  {
    "timestamp": "03/27/2024 01:40:10.073403",
    "simulationTimeStamp": "258.2175",
    "logType": "Rerouting",
    "eventType": "Rerouting Option Previewed",
    "logMessages": [
      "Rerouting option previewed for Uav Charlie ",
      "Path start time: 03/27/2024 01:40:10.039657",
      "Previewed route is good"
    ],
    "logGenerator": "Client"
  },
  {
    "timestamp": "03/27/2024 01:40:10.073403",
    "simulationTimeStamp": "258.2175",
    "logType": "Rerouting",
    "eventType": "Rerouting Option Previewed",
    "logMessages": [
      "Rerouting option previewed for Uav India ",
      "Path start time: 03/27/2024 01:40:10.040664",
      "Previewed route is good"
    ],
    "logGenerator": "Client"
  },
  {
    "timestamp": "03/27/2024 01:40:10.073403",
    "simulationTimeStamp": "258.2175",
    "logType": "Rerouting",
    "eventType": "Rerouting Option Previewed",
    "logMessages": [
      "Rerouting option previewed for Uav India ",
      "Path start time: 03/27/2024 01:40:10.040664",
      "Previewed route is good"
    ],
    "logGenerator": "Client"
  },
  {
    "timestamp": "03/27/2024 01:41:23.986421",
    "simulationTimeStamp": "269.601",
    "logType": "Rerouting",
    "eventType": "Rerouting Options Requested",
    "logMessages": [
      " requested rerouting options for uav Nectar",
      "Path start time: 03/27/2024 01:40:10.041664",
      "Rerouting is not needed"
    ],
    "logGenerator": "Client"
  },
  {
    "timestamp": "03/27/2024 01:41:25.906249",
    "simulationTimeStamp": "271.5296",
    "logType": "Rerouting",
    "eventType": "Rerouting Option Previewed",
    "logMessages": [
      "Rerouting option previewed for Uav Nectar ",
      "Path start time: 03/27/2024 01:40:10.041664",
      "Previewed route is good"
    ],
    "logGenerator": "Client"
  },
  {
    "timestamp": "03/27/2024 01:41:26.502547",
    "simulationTimeStamp": "272.123",
    "logType": "Uav",
    "eventType": "ConditionChanged",
    "logMessages": [
      "Uav Papa condition changed to Enabled"
    ],
    "logGenerator": "None"
  },
  {
    "timestamp": "03/27/2024 01:41:26.564040",
    "simulationTimeStamp": "272.1854",
    "logType": "Uav",
    "eventType": "ConditionChanged",
    "logMessages": [
      "Uav Alfa condition changed to Hidden"
    ],
    "logGenerator": "None"
  },
  {
    "timestamp": "03/27/2024 01:41:26.564040",
    "simulationTimeStamp": "272.1854",
    "logType": "Uav",
    "eventType": "ConditionChanged",
    "logMessages": [
      "Uav Bravo condition changed to Hidden"
    ],
    "logGenerator": "None"
  },
  {
    "timestamp": "03/27/2024 01:41:26.564040",
    "simulationTimeStamp": "272.1854",
    "logType": "Uav",
    "eventType": "ConditionChanged",
    "logMessages": [
      "Uav Charlie condition changed to Hidden"
    ],
    "logGenerator": "None"
  },
  {
    "timestamp": "03/27/2024 01:41:26.564040",
    "simulationTimeStamp": "272.1854",
    "logType": "Uav",
    "eventType": "ConditionChanged",
    "logMessages": [
      "Uav Delta condition changed to Hidden"
    ],
    "logGenerator": "None"
  },
  {
    "timestamp": "03/27/2024 01:41:26.564040",
    "simulationTimeStamp": "272.1854",
    "logType": "Uav",
    "eventType": "ConditionChanged",
    "logMessages": [
      "Uav Echo condition changed to Hidden"
    ],
    "logGenerator": "None"
  },
  {
    "timestamp": "03/27/2024 01:41:26.565038",
    "simulationTimeStamp": "272.1854",
    "logType": "Uav",
    "eventType": "ConditionChanged",
    "logMessages": [
      "Uav Frank condition changed to Enabled"
    ],
    "logGenerator": "None"
  },
  {
    "timestamp": "03/27/2024 01:41:26.565038",
    "simulationTimeStamp": "272.1854",
    "logType": "Uav",
    "eventType": "ConditionChanged",
    "logMessages": [
      "Uav Golf condition changed to Hidden"
    ],
    "logGenerator": "None"
  },
  {
    "timestamp": "03/27/2024 01:41:26.565038",
    "simulationTimeStamp": "272.1854",
    "logType": "Uav",
    "eventType": "ConditionChanged",
    "logMessages": [
      "Uav Hotel condition changed to Hidden"
    ],
    "logGenerator": "None"
  },
  {
    "timestamp": "03/27/2024 01:41:26.565038",
    "simulationTimeStamp": "272.1854",
    "logType": "Uav",
    "eventType": "ConditionChanged",
    "logMessages": [
      "Uav India condition changed to Hidden"
    ],
    "logGenerator": "None"
  },
  {
    "timestamp": "03/27/2024 01:41:26.565038",
    "simulationTimeStamp": "272.1854",
    "logType": "Uav",
    "eventType": "ConditionChanged",
    "logMessages": [
      "Uav John condition changed to Hidden"
    ],
    "logGenerator": "None"
  },
  {
    "timestamp": "03/27/2024 01:41:26.565038",
    "simulationTimeStamp": "272.1854",
    "logType": "Uav",
    "eventType": "ConditionChanged",
    "logMessages": [
      "Uav Kilo condition changed to Hidden"
    ],
    "logGenerator": "None"
  },
  {
    "timestamp": "03/27/2024 01:41:26.566042",
    "simulationTimeStamp": "272.1854",
    "logType": "Uav",
    "eventType": "ConditionChanged",
    "logMessages": [
      "Uav Lima condition changed to Enabled"
    ],
    "logGenerator": "None"
  },
  {
    "timestamp": "03/27/2024 01:41:26.566042",
    "simulationTimeStamp": "272.1854",
    "logType": "Uav",
    "eventType": "ConditionChanged",
    "logMessages": [
      "Uav Mike condition changed to Hidden"
    ],
    "logGenerator": "None"
  },
  {
    "timestamp": "03/27/2024 01:41:26.566042",
    "simulationTimeStamp": "272.1854",
    "logType": "Uav",
    "eventType": "ConditionChanged",
    "logMessages": [
      "Uav Nectar condition changed to Enabled"
    ],
    "logGenerator": "None"
  },
  {
    "timestamp": "03/27/2024 01:41:26.566042",
    "simulationTimeStamp": "272.1854",
    "logType": "Uav",
    "eventType": "ConditionChanged",
    "logMessages": [
      "Uav Oscar condition changed to Hidden"
    ],
    "logGenerator": "None"
  },
  {
    "timestamp": "03/27/2024 01:41:26.608836",
    "simulationTimeStamp": "272.2321",
    "logType": "Rerouting",
    "eventType": "Rerouting Option Previewed",
    "logMessages": [
      "Rerouting option previewed for Uav Nectar ",
      "Path start time: 03/27/2024 01:41:26.566042",
      "Previewed route is good"
    ],
    "logGenerator": "Client"
  },
  {
    "timestamp": "03/27/2024 01:41:26.608836",
    "simulationTimeStamp": "272.2321",
    "logType": "Rerouting",
    "eventType": "Rerouting Option Previewed",
    "logMessages": [
      "Rerouting option previewed for Uav Nectar ",
      "Path start time: 03/27/2024 01:41:26.566042",
      "Previewed route is good"
    ],
    "logGenerator": "Client"
  },
  {
    "timestamp": "03/27/2024 01:41:27.461827",
    "simulationTimeStamp": "273.0837",
    "logType": "Fuel",
    "eventType": "Fuel Condition Changed",
    "logMessages": [
      "UAV India fuel leak event started"
    ],
    "logGenerator": "None"
  },
  {
    "timestamp": "03/27/2024 01:41:27.848704",
    "simulationTimeStamp": "273.4632",
    "logType": "Rerouting",
    "eventType": "Rerouting Options Requested",
    "logMessages": [
      " requested rerouting options for uav Nectar",
      "Path start time: 03/27/2024 01:41:26.566042",
      "Rerouting is not needed"
    ],
    "logGenerator": "Client"
  },
  {
    "timestamp": "03/27/2024 01:41:28.983084",
    "simulationTimeStamp": "274.606",
    "logType": "Rerouting",
    "eventType": "Rerouting Option Previewed",
    "logMessages": [
      "Rerouting option previewed for Uav Nectar ",
      "Path start time: 03/27/2024 01:41:26.566042",
      "Previewed route is good"
    ],
    "logGenerator": "Client"
  },
  {
    "timestamp": "03/27/2024 01:41:31.190039",
    "simulationTimeStamp": "276.8128",
    "logType": "Rerouting",
    "eventType": "Rerouting Option Previewed",
    "logMessages": [
      "Rerouting option previewed for Uav Nectar ",
      "Path start time: 03/27/2024 01:41:26.566042",
      "Previewed route is good"
    ],
    "logGenerator": "Client"
  },
  {
    "timestamp": "03/27/2024 01:41:37.465887",
    "simulationTimeStamp": "283.0873",
    "logType": "Fuel",
    "eventType": "Fuel Condition Changed",
    "logMessages": [
      "UAV India fuel leak became fatal "
    ],
    "logGenerator": "None"
  },
  {
    "timestamp": "03/27/2024 01:41:39.633293",
    "simulationTimeStamp": "285.2538",
    "logType": "Fuel",
    "eventType": "Fuel Condition Changed",
    "logMessages": [
      "UAV Nectar fuel became empty and it stopped navigating"
    ],
    "logGenerator": "None"
  },
  {
    "timestamp": "03/27/2024 01:41:39.633293",
    "simulationTimeStamp": "285.2538",
    "logType": "Uav",
    "eventType": "ConditionChanged",
    "logMessages": [
      "Uav Nectar condition changed to Lost"
    ],
    "logGenerator": "None"
  },
  {
    "timestamp": "03/27/2024 01:41:39.735022",
    "simulationTimeStamp": "285.3582",
    "logType": "Rerouting",
    "eventType": "Rerouting Option Previewed",
    "logMessages": [
      "Rerouting option previewed for Uav Nectar ",
      "Path start time: 03/27/2024 01:41:26.566042",
      "Previewed route is good"
    ],
    "logGenerator": "Client"
  },
  {
    "timestamp": "03/27/2024 01:41:40.521082",
    "simulationTimeStamp": "286.1433",
    "logType": "Uav",
    "eventType": "ConditionChanged",
    "logMessages": [
      "Uav Papa condition changed to Hidden"
    ],
    "logGenerator": "None"
  },
  {
    "timestamp": "03/27/2024 01:41:40.576726",
    "simulationTimeStamp": "286.1983",
    "logType": "Uav",
    "eventType": "ConditionChanged",
    "logMessages": [
      "Uav Alfa condition changed to Hidden"
    ],
    "logGenerator": "None"
  },
  {
    "timestamp": "03/27/2024 01:41:40.576726",
    "simulationTimeStamp": "286.1983",
    "logType": "Uav",
    "eventType": "ConditionChanged",
    "logMessages": [
      "Uav Bravo condition changed to Enabled"
    ],
    "logGenerator": "None"
  },
  {
    "timestamp": "03/27/2024 01:41:40.576726",
    "simulationTimeStamp": "286.1983",
    "logType": "Uav",
    "eventType": "ConditionChanged",
    "logMessages": [
      "Uav Charlie condition changed to Hidden"
    ],
    "logGenerator": "None"
  },
  {
    "timestamp": "03/27/2024 01:41:40.576726",
    "simulationTimeStamp": "286.1983",
    "logType": "Uav",
    "eventType": "ConditionChanged",
    "logMessages": [
      "Uav Delta condition changed to Enabled"
    ],
    "logGenerator": "None"
  },
  {
    "timestamp": "03/27/2024 01:41:40.576726",
    "simulationTimeStamp": "286.1983",
    "logType": "Uav",
    "eventType": "ConditionChanged",
    "logMessages": [
      "Uav Echo condition changed to Hidden"
    ],
    "logGenerator": "None"
  },
  {
    "timestamp": "03/27/2024 01:41:40.577944",
    "simulationTimeStamp": "286.1983",
    "logType": "Uav",
    "eventType": "ConditionChanged",
    "logMessages": [
      "Uav Frank condition changed to Hidden"
    ],
    "logGenerator": "None"
  },
  {
    "timestamp": "03/27/2024 01:41:40.577944",
    "simulationTimeStamp": "286.1983",
    "logType": "Uav",
    "eventType": "ConditionChanged",
    "logMessages": [
      "Uav Golf condition changed to Hidden"
    ],
    "logGenerator": "None"
  },
  {
    "timestamp": "03/27/2024 01:41:40.577944",
    "simulationTimeStamp": "286.1983",
    "logType": "Uav",
    "eventType": "ConditionChanged",
    "logMessages": [
      "Uav Hotel condition changed to Hidden"
    ],
    "logGenerator": "None"
  },
  {
    "timestamp": "03/27/2024 01:41:40.577944",
    "simulationTimeStamp": "286.1983",
    "logType": "Uav",
    "eventType": "ConditionChanged",
    "logMessages": [
      "Uav India condition changed to Hidden"
    ],
    "logGenerator": "None"
  },
  {
    "timestamp": "03/27/2024 01:41:40.578449",
    "simulationTimeStamp": "286.1983",
    "logType": "Uav",
    "eventType": "ConditionChanged",
    "logMessages": [
      "Uav John condition changed to Hidden"
    ],
    "logGenerator": "None"
  },
  {
    "timestamp": "03/27/2024 01:41:40.578449",
    "simulationTimeStamp": "286.1983",
    "logType": "Uav",
    "eventType": "ConditionChanged",
    "logMessages": [
      "Uav Kilo condition changed to Hidden"
    ],
    "logGenerator": "None"
  },
  {
    "timestamp": "03/27/2024 01:41:40.578449",
    "simulationTimeStamp": "286.1983",
    "logType": "Uav",
    "eventType": "ConditionChanged",
    "logMessages": [
      "Uav Lima condition changed to Hidden"
    ],
    "logGenerator": "None"
  },
  {
    "timestamp": "03/27/2024 01:41:40.578449",
    "simulationTimeStamp": "286.1983",
    "logType": "Uav",
    "eventType": "ConditionChanged",
    "logMessages": [
      "Uav Mike condition changed to Enabled"
    ],
    "logGenerator": "None"
  },
  {
    "timestamp": "03/27/2024 01:41:40.578449",
    "simulationTimeStamp": "286.1983",
    "logType": "Uav",
    "eventType": "ConditionChanged",
    "logMessages": [
      "Uav Oscar condition changed to Enabled"
    ],
    "logGenerator": "None"
  },
  {
    "timestamp": "03/27/2024 01:41:42.822670",
    "simulationTimeStamp": "288.4383",
    "logType": "Rerouting",
    "eventType": "Rerouting Options Requested",
    "logMessages": [
      " requested rerouting options for uav Oscar",
      "Path start time: 03/27/2024 01:41:40.578449",
      "Rerouting is not needed"
    ],
    "logGenerator": "Client"
  },
  {
    "timestamp": "03/27/2024 01:41:44.122660",
    "simulationTimeStamp": "289.7442",
    "logType": "Rerouting",
    "eventType": "Rerouting Option Previewed",
    "logMessages": [
      "Rerouting option previewed for Uav Oscar ",
      "Path start time: 03/27/2024 01:41:40.578449",
      "Previewed route is good"
    ],
    "logGenerator": "Host"
  },
  {
    "timestamp": "03/27/2024 01:41:44.122660",
    "simulationTimeStamp": "289.7442",
    "logType": "Rerouting",
    "eventType": "Rerouting Option Previewed",
    "logMessages": [
      "Rerouting option previewed for Uav Oscar ",
      "Path start time: 03/27/2024 01:41:40.578449",
      "Previewed route is good"
    ],
    "logGenerator": "Client"
  }
]